Workbook

Sheet P&L 2022-2024
B2: VioTrans Group SRL | C2: Source: https://www.ecb.europa.eu/stats/policy_and_exchange_rates/euro_reference_exchange_rates/html/eurofxref-graph-ron.de.html
C3: EUR vs. RON | E3: EUR vs. RON | G3: EUR vs. RON
B4: In € | C4: 46021 | E4: 45655 | G4: 45657
C5: 4.949 | E5: 4.975 | G5: 4.974
B7: No. Description | C7: for the period ended December 31, 2022 | E7: for the period ended December 31, 2023 | G7: for the period ended December 31, 2024
B8: 1. Net turnover (row 03 + 04 - 05 + 06) | C8: 38216486 | D8: =C8/C24 -> 0.9884008 | E8: 37396294 | F8: =E8/E24 -> 0.98546718 | G8: 34006909 | H8: =G8/G24 -> 0.98263516
B9: - out of which net turnover for the main activity | C9: 0 | E9: 0 | G9: 32096156
B10: - out of which, the net turnover achieved from operations carried out on national territory | C10: 0 | E10: 0 | G10: 341506.25
B11: Sales of goods (acc. 701 + 702 + 703 + 704 + 705 + 706 + 708) | C11: 36069540 | D11: =C11/C24 -> 0.93287391 | E11: 0 | F11: =E11/E24 -> 0 | G11: 32197889 | H11: =G11/G24 -> 0.93036324
B12: Sales of merchandise (acc. 707) | C12: 2146945.6 | D12: =C12/C24 -> 0.055526895 | E12: 0 | F12: =E12/E24 -> 0 | G12: 1809019.5 | H12: =G12/G24 -> 0.052271913
B13: Discounts granted (acc. 709) | C13: 0 | E13: 0 | G13: 0
B14: Revenue from operating subsidies related to the turnover (acc. 7411) | C14: 0 | E14: 0 | G14: 0
B15: 2. Revenue related to the cost of the work in progress (acc. 711+712) - Cr Balance | C15: 0 | E15: 0 | G15: 0
B16: Revenue related to the cost of the work in progress (acc. 711 + 712) - Dr Balance | C16: 0 | E16: 0 | G16: 0
B17: 3. Income from production of tangible and intangible assets (acc. 721 + 722) | C17: 0 | E17: 0 | G17: 0
B18: 4. Income from the revaluation of tangible assets (acc. 755) | C18: 0 | E18: 0 | G18: 0
B19: 5. Income from production of real estate investments (acc. 725) | C19: 0 | E19: 0 | G19: 0
B20: 6. Income from operating subsidies (acc. 7412 + 7413 + 7414 + 7415 + 7416 + 7417 + 7419) | C20: 0 | E20: 0 | G20: 0
B21: 7. Other operating income (acc. 751 + 758 + 7815) | C21: 448482.52 | D21: =C21/C24 -> 0.011599195 | E21: 551488.24 | F21: =E21/E24 -> 0.014532819 | G21: 600960.19 | H21: =G21/G24 -> 0.017364843
B22: - out of which, income from investment subsidies (acc. 7584) | C22: 6159.6282 | D22: =C22/C24 -> 0.00015930773 | E22: 0 | G22: 0
B23: - out of which, income from negative goodwill (acc. 7815) | C23: 0 | E23: 0 | G23: 0
B24: OPERATING INCOME – TOTAL (rows 01 + 07 – 08 + 09 + 10 + 11 + 12 + 13) | C24: 38664968 | D24: =SUM(D11:D23) -> 1.0001593 | E24: 37947783 | F24: =SUM(F11:F23) -> 0.014532819 | G24: 34607869 | H24: =SUM(H11:H23) -> 1
B25: Growth in % | E25: =E24/C24-1 -> -0.018548728 | G25: =G24/E24-1 -> -0.088013411
B26: 8. a) Expenses related to raw materials and consumables (acc. 601 + 602) | C26: 6764286.9 | D26: =C$26/$C$24 -> 0.17494614 | E26: 6514435.2 | F26: =E$26/$E$24 -> 0.1716684 | G26: 5768370.5 | H26: =G$26/$G$24 -> 0.16667801
B27: Other material expenses (acc. 603 + 604 + 606 + 608) | C27: 30171.752 | D27: =$C27/$C$24 -> 0.0007803382 | E27: 33208.442 | F27: =$E27/$E$24 -> 0.0008751089 | G27: 21910.334 | H27: =$G27/$G$24 -> 0.00063310266
B28: b) Other external expenses (power and water supply) (acc. 605) | C28: 86376.44 | D28: =$C28/$C$24 -> 0.0022339716 | E28: 61133.065 | F28: =$E28/$E$24 -> 0.0016109786 | G28: 40715.32 | H28: =$G28/$G$24 -> 0.0011764758
B29: - out of which, expenses with power consumption (acc. 6051) | C29: 84990.099 | D29: =$C29/$C$24 -> 0.0021981163 | E29: 58890.452 | F29: =$E29/$E$24 -> 0.0015518813 | G29: 37208.484 | H29: =$G29/$G$24 -> 0.0010751452
B30: - out of which, expenses with natural gas consumption (acc. 6053) | C30: 0 | E30: 0 | G30: 0
B31: c) Merchandise expenses (acc. 607) | C31: 2145422.1 | D31: =$C31/$C$24 -> 0.055487491 | E31: 1748810.5 | F31: =$E31/$E$24 -> 0.046084655 | G31: 1808855.6 | H31: =$G31/$G$24 -> 0.052267178
B32: Commercial discounts received (acc. 609) | C32: 0 | E32: 0 | G32: 0
B33: 9. Personnel expenses (rows 25 + 26), out of which: | C33: 3420668.4 | D33: =$C33/$C$24 -> 0.088469448 | E33: 4168543.1 | F33: =$E33/$E$24 -> 0.10984945 | G33: 4283540.6 | H33: =$G33/$G$24 -> 0.1237736
B34: a) Salaries and allowance (acc. 641 + 642 + 643 + 644) | C34: 3347551.6 | D34: =$C34/$C$24 -> 0.086578413 | E34: 4079188.7 | F34: =$E34/$E$24 -> 0.10749479 | G34: 4188603.7 | H34: =$G34/$G$24 -> 0.12103039
B35: b) Social security (acc. 645 + 646) | C35: 73116.791 | D35: =$C35/$C$24 -> 0.0018910346 | E35: 89354.372 | F35: =$E35/$E$24 -> 0.0023546665 | G35: 94936.872 | H35: =$G35/$G$24 -> 0.0027432164
B36: 10. a) Value adjustments regarding tangible and intangible assets (rows 28+29-30) | C36: 2860043.2 | D36: =$C36/$C$24 -> 0.073969884 | E36: 2910385.1 | F36: =$E36/$E$24 -> 0.076694472 | G36: 2502104.1 | H36: =$G36/$G$24 -> 0.072298706
B37: a. 1) Expenses with depreciation and amortisation (acc. 6811) | C37: 2860043.2 | D37: =$C37/$C$24 -> 0.073969884 | E37: 2910385.1 | F37: =$E37/$E$24 -> 0.076694472 | G37: 2502104.1 | H37: =$G37/$G$24 -> 0.072298706
B38: a. 2) Other expenses (acc. 6813 + 6817+ from acc. 6818) | C38: 0 | E38: 0 | G38: 0
B39: a. 3) Income (acc. 7813 + from acc. 7818) | C39: 0 | E39: 0 | G39: 0
B40: 10. b) Value adjustments regarding current assets (rows 31 – 32) | C40: 1497.2722 | D40: =$C40/$C$24 -> 3.8724257e-05 | E40: -6619.2965 | F40: =$E40/$E$24 -> -0.00017443171 | G40: 36502.01 | H40: =$G40/$G$24 -> 0.0010547315
B41: b. 1) Expenses (acc. 654 + 6814 + from acc. 6818) | C41: 60289.351 | D41: =$C41/$C$24 -> 0.0015592758 | E41: 8057.2864 | F41: =$E41/$E$24 -> 0.00021232562 | G41: 48636.711 | H41: =$G41/$G$24 -> 0.0014053657
B42: b. 2) Income (acc. 754 + 7814 + from acc. 7818) | C42: 58792.079 | D42: =$C42/$C$24 -> 0.0015205516 | E42: 14676.583 | F42: =$E42/$E$24 -> 0.00038675733 | G42: 12134.7 | H42: =$G42/$G$24 -> 0.00035063414
B43: 11. Other operating expenses (rows 35 + 36 + 40 + 42 + 44 + 46 + 47 + 48 + 49 + 50) | C43: 20860357 | D43: =SUM(D44:D59) -> 0.53951993 | E43: 20773838 | F43: =$E43/$E$24 -> 0.5474322 | G43: 19593999 | H43: =$G43/$G$24 -> 0.56617178
B44: 11.1. External services expenses (acc. 611 + 613 + 614 + 615 + 621 + 622 + 623 + 624 + 625 + 626 + 627 + 628) | C44: 20609084 | D44: =$C44/$C$24 -> 0.53301695 | E44: 20097555 | F44: =$E44/$E$24 -> 0.52961078 | G44: 19154840 | H44: =$G44/$G$24 -> 0.55348221
B45: 11.2.Expenses with Royalties, management leases and rental (acc. 612) | C45: 164.07355 | D45: =$C45/$C$24 -> 4.2434678e-06 | E45: 35171.457 | F45: =$E45/$E$24 -> 0.00092683828 | G45: 85481.303 | H45: =$G45/$G$24 -> 0.0024699962
B46: - Expenses with Royalties (acc. 6121) | C46: 0 | E46: 0 | G46: 0
B47: - Expenses with Management leases (acc. 6122) | C47: 0 | E47: 0 | G47: 0
B48: - Expenses with Rent expenses (acc. 6123) | C48: 164.07355 | D48: =$C48/$C$24 -> 4.2434678e-06 | E48: 35171.457 | F48: =$E48/$E$24 -> 0.00092683828 | G48: 85481.303 | H48: =$G48/$G$24 -> 0.0024699962
B49: 11.2.Expenses with Intellectual property rights (acc. 616) | C49: 0 | E49: 0 | G49: 0
B50: - of which, expenses related to affiliates | C50: 0 | E50: 0 | G50: 0
B51: 11.4. Expenses with management (acc. 617*) | C51: 0 | E51: 0 | G51: 0
B52: - of which, expenses related to affiliates | C52: 0 | E52: 0 | G52: 0
B53: 11.5. Expenses with consulting (acc. 618) | C53: 0 | E53: 0 | G53: 0
B54: - of which, expenses related to affiliates | C54: 0 | E54: 0 | G54: 0
B55: 11.6. Expenses with other taxes, charges and similar expenses; Transfers and contributions owed based on special acts of legislation (acc. 635 + 6586) | C55: 101415.24 | D55: =$C55/$C$24 -> 0.002622923 | E55: 107909.35 | F55: =$E55/$E$24 -> 0.0028436272 | G55: 126989.14 | H55: =$G55/$G$24 -> 0.003669372
B56: 11.7. Expenses with environmental protection (acc. 652) | C56: 0 | E56: 0 | G56: 0
B57: 11.8. Expenses related to revaluation of tangible assets (acc. 655) | C57: 0 | E57: 0 | G57: 0
B58: 11.9. Expenses related to natural disasters and other similar events (acc. 6587) | C58: 0 | E58: 0 | G58: 0
B59: 11.10. Other expenses (acc. 651 + 6581 + 6582 + 6583 + 6584 + 6588) | C59: 149693.88 | D59: =$C59/$C$24 -> 0.0038715634 | E59: 533202.61 | F59: =$E59/$E$24 -> 0.014050956 | G59: 226688.58 | H59: =$G59/$G$24 -> 0.0065502034
B60: 12. Adjustments regarding the provisions (rows 52 – 53) | C60: 0 | E60: 0 | G60: 0 | H60: =$G60/$G$24 -> 0
B61: - Expenses (acc. 6812) | C61: 0 | E61: 0 | G61: 0
B62: - Income (acc. 7812) | C62: 0 | E62: 0 | G62: 0
B63: OPERATING EXPENSES – TOTAL (rows 17 + 18 + 19 + 22 – 23 + 24 + 27 + 31 + 34 + 51) | C63: 36168823 | D63: =$C63/$C$24 -> 0.93544168 | E63: 36203734 | F63: =$E63/$E$24 -> 0.95404083 | G63: 34055997 | H63: =$G63/$G$24 -> 0.98405358
B64: OPERATING PROFIT OR LOSS | C64: 0 | E64: 0 | G64: 0
B65: - Profit (rows 16 – 54) | C65: 2496145.5 | D65: =$C65/$C$24 -> 0.064558322 | E65: 1744048.4 | F65: =$E65/$E$24 -> 0.045959166 | G65: 551871.53 | H65: =$G65/$G$24 -> 0.015946418
B66: - Loss (rows 54 – 16) | C66: 0 | E66: 0 | G66: 0
B67: 13. Income from participating interests (acc. 7611 + 7612 + 7613) | C67: 0 | E67: 0 | G67: 0
B68: of which, income from affiliates | C68: 0 | E68: 0 | G68: 0
B69: Growth in % | E69: =E65/C65-1 -> -0.30130337 | G69: =G65/E65-1 -> -0.68356869
B70: 14. Interest income (acc. 766) | C70: 73234.189 | D70: =$C70/$C$24 -> 0.0018940708 | E70: 232947.54 | F70: =$E70/$E$24 -> 0.0061386337 | G70: 228424.41 | H70: =$G70/$G$24 -> 0.0066003604
B71: - of which, income from affiliates | C71: 21972.396 | D71: =$C71/$C$24 -> 0.00056827659 | E71: 209530.25 | F71: =$E71/$E$24 -> 0.0055215414 | G71: 195674.11 | H71: =$G71/$G$24 -> 0.0056540351
B72: 15. Income from operating subsidies for interest payable (acc. 7418) | C72: 0 | E72: 0 | G72: 0
B73: 16. Other financial income (acc. 7615 + 762 + 764 + 765 + 767 + 768) | C73: 506588.4 | D73: =$C73/$C$24 -> 0.013102 | E73: 541952.96 | F73: =$E73/$E$24 -> 0.014281545 | G73: 182803.38 | H73: =$G73/$G$24 -> 0.0052821334
B74: - of which, income from financial assets (acc. 7615) | C74: 0 | E74: 0 | G74: 0
B75: FINANCIAL INCOME – TOTAL (rows 57 + 59 + 61 + 62) | C75: 579822.59 | D75: =$C75/$C$24 -> 0.01499607 | E75: 774900.5 | F75: =$E75/$E$24 -> 0.020420179 | G75: 411227.78 | H75: =$G75/$G$24 -> 0.011882494
B76: 17. Value adjustments regarding the financial assets and financial investments held as current assets (rows 66-67) | C76: 0 | E76: 0 | G76: 0 | H76: =$G76/$G$24 -> 0
B77: Expenses (acc. 686) | C77: 0 | E77: 0 | G77: 0
B78: Income (acc. 786) | C78: 0 | E78: 0 | G78: 0
B79: 18. Interest expenses (acc. 666*) | C79: 281040.01 | D79: =$C79/$C$24 -> 0.0072685953 | E79: 407228.74 | F79: =$E79/$E$24 -> 0.010731292 | G79: 333678.53 | H79: =$G79/$G$24 -> 0.0096416954
B80: - of which, expenses related to affiliates | C80: 465.34653 | D80: =$C80/$C$24 -> 1.2035353e-05 | E80: 0 | G80: 0
B81: 19. Other financial expenses (acc. 663 + 664 + 665 + 667 + 668) | C81: 455423.12 | D81: =$C81/$C$24 -> 0.011778701 | E81: 549921.01 | F81: =$E81/$E$24 -> 0.014491519 | G81: 137559.11 | H81: =$G81/$G$24 -> 0.0039747928
B82: FINANCIAL EXPENSES – TOTAL (rows 65 + 68 + 70) | C82: 736463.12 | D82: =$C82/$C$24 -> 0.019047297 | E82: 957149.75 | F82: =$E82/$E$24 -> 0.025222811 | G82: 471237.64 | H82: =$G82/$G$24 -> 0.013616488
B83: - Profit (row 64 – 71) | C83: 0 | E83: 0 | G83: 0
B84: - Loss (row 71 – 64) | C84: 156640.53 | D84: =$C84/$C$24 -> 0.0040512262 | E84: 182249.25 | F84: =$E84/$E$24 -> 0.0048026323 | G84: 60009.851 | H84: =$G84/$G$24 -> 0.0017339944
B85: TOTAL INCOME (rows 16 + 64) | C85: 39244791 | D85: =$C85/$C$24 -> 1.0149961 | E85: 38722683 | F85: =$E85/$E$24 -> 1.0204202 | G85: 35019097 | H85: =$G85/$G$24 -> 1.0118825
B86: TOTAL EXPENSES (rows 54 + 71) | C86: 36905286 | D86: =$C86/$C$24 -> 0.95448897 | E86: 37160884 | F86: =$E86/$E$24 -> 0.97926364 | G86: 34527235 | H86: =$G86/$G$24 -> 0.99767007
B87: GROSS PROFIT OR LOSS | C87: 0 | E87: 0 | G87: 0
B88: - Profit (row 74 - 75) | C88: 2339505 | D88: =$C88/$C$24 -> 0.060507096 | E88: 1561799.2 | F88: =$E88/$E$24 -> 0.041156534 | G88: 491861.68 | H88: =$G88/$G$24 -> 0.014212423
B89: - Loss (row 75 - 74) | C89: 0 | E89: 0 | G89: 0
B90: 20. Income Tax (acc. 691) | C90: 364367.75 | D90: =$C90/$C$24 -> 0.0094237178 | E90: 270599.8 | F90: =$E90/$E$24 -> 0.0071308462 | G90: 132156.41 | H90: =$G90/$G$24 -> 0.0038186811
C91: 0 | E91: 0 | G91: 0
B92: 21. Expenses with income tax, including minimum turnover tax, resulting from income tax settlements in the tax group (acc. 694) | C92: 0 | E92: 0 | G92: 0
C93: 0 | E93: 0 | G93: 0
B94: 22. Income from income tax, including minimum turnover tax, resulting from income tax settlements in the tax group (acc. 794) | C94: 0 | E94: 0 | G94: 0
C95: 0 | E95: 0 | G95: 0
B96: 23. Expenses with income tax at the level of the minimum turnover tax (acc. 697) | C96: 0 | E96: 0 | G96: 0
B97: 24. Other taxes not included in the captions above (acc. 698) | C97: 0 | E97: 0 | G97: 0
B98: NET PROFIT OR LOSS FOR THE REPORTING PERIOD - Profit (rows 76 – 78 – 79 – 81 – 82 + 80) | C98: 1975137.2 | D98: =$C98/$C$24 -> 0.051083378 | E98: 1291199.4 | F98: =$E98/$E$24 -> 0.034025688 | G98: 359705.27 | H98: =$G98/$G$24 -> 0.010393742
B99: - Loss (rows 77 + 78 + 79 + 81 + 82 - 80); (rows 78 + 79 + 81 + 82 – 76 – 80) | C99: 0 | E99: 0 | G99: 0
B100: Growth in % | E100: =E98/C98-1 -> -0.34627357 | G100: =G98/E98-1 -> -0.72141772
B104: EBIT | C104: =C98+C90+C82-C75 -> 2496145.5 | E104: =E98+E90+E82-E75 -> 1744048.4 | G104: =G98+G90+G82-G75 -> 551871.53
C105: =C104/C24 -> 0.064558322 | E105: =E104/E24 -> 0.045959166 | G105: =G104/G24 -> 0.015946418
...

Sheet Balance Sheet 2022-2024
B2: VioTrans Group SRL | C2: Source: https://www.ecb.europa.eu/stats/policy_and_exchange_rates/euro_reference_exchange_rates/html/eurofxref-graph-ron.de.html
C3: EUR vs. RON | E3: EUR vs. RON | G3: EUR vs. RON
B4: In € | C4: 46021 | E4: 45655 | G4: 45657
C5: 4.949 | E5: 4.975 | G5: 4.974
B7: No. Description | C7: as at December 31, 2022 | E7: as at December 31, 2023 | G7: as at December 31, 2024
B8: NON-CURRENT ASSETS
B9: I. INTANGIBLE ASSETS
B10: 1 Set-up expenses (acc. 201 - 2801) | C10: 0 | E10: 0 | G10: 0
B11: 2 Development expenses (acc. 2023 - 2803 - 2903) | C11: 0 | E11: 0 | G11: 0
B12: 3 Concessions, patents, licenses, trademarks, similar rights and assets and other intangible assets (acc. 205 + 208 - 2805 - 2808 - 2905 - 2908) | C12: 4011.3154 | D12: =C12/C37 -> 0.00041856634 | E12: 25585.528 | F12: =E12/E37 -> 0.0034451766 | G12: 19983.514 | H12: =G12/G37 -> 0.0038357813
B13: 4 Goodwill (acc. 2071 - 2807) | C13: 0 | E13: 0 | G13: 0
B14: 5 Intangible exploration assets and evaluation of mineral resources (206 - 2806 - 2906) | C14: 0 | E14: 0 | G14: 0
B15: 6 Advances (acc. 4094 - 4904) | C15: 0 | E15: 0 | G15: 0
B16: TOTAL (row 01 to 06) | C16: 4011.3154 | D16: =C16/C66 -> 0.00019013009 | E16: 25585.528 | F16: =E16/E66 -> 0.0013602633 | G16: 19983.514 | H16: =G16/G66 -> 0.0012980413
B17: II. TANGIBLE ASSETS | C17: 0 | E17: 0 | G17: 0
B18: 1 Land and buildings (acc. 211 + 212 - 2811 - 2812 - 2911 - 2912) | C18: 1523198.8 | D18: =$C18/$C$66 -> 0.072197246 | E18: 1452865.5 | F18: =$E18/$E$66 -> 0.077242091 | G18: 1370667.7 | H18: =$G18/$G$66 -> 0.08903255
B19: 2 Installations and machinery (acc. 213 + 223 - 2813 - 2913) | C19: 7850724.8 | D19: =$C19/$C$66 -> 0.37211209 | E19: 5860386.3 | F19: =$E19/$E$66 -> 0.31156944 | G19: 3554068 | H19: =$G19/$G$66 -> 0.23085664
B20: 3 Other installations, machines and furniture (acc. 214 + 224 - 2814 - 2914) | C20: 76867.448 | D20: =$C20/$C$66 -> 0.003643397 | E20: 77261.709 | F20: =$E20/$E$66 -> 0.0041076451 | G20: 154964.82 | H20: =$G20/$G$66 -> 0.010065834
B21: 4 Investment property (acc. 215 - 2815 - 2915) | C21: 0 | E21: 0 | G21: 0
B22: 5 Tangible assets in progress (acc. 231 - 2931) | C22: 4992.5237 | D22: =$C22/$C$66 -> 0.00023663783 | E22: 0 | G22: 0
B23: 6 Investment property in progress (acc. 235 - 2935) | C23: 0 | E23: 0 | G23: 0
B24: 7 Tangible assets for exploration and valuation of mineral resources (acc. 216 - 2816 - 2916) | C24: 0 | E24: 0 | G24: 0
B25: 8 Productive biological assets (acc. 217 + 227 - 2817 - 2917) | C25: 0 | E25: 0 | G25: 0
B26: 9 Advances (acc. 4093 - 4903) | C26: 120859.57 | D26: =$C26/$C$66 -> 0.0057285547 | E26: 0 | G26: 100002.01 | H26: =$G26/$G$66 -> 0.0064956913
B27: TOTAL (row 08 to 16) | C27: 9576643.2 | D27: =$C27/$C$66 -> 0.45391793 | E27: 7390513.6 | F27: =$E27/$E$66 -> 0.39291917 | G27: 5179702.5 | H27: =$G27/$G$66 -> 0.33645071
B28: III. FINANCIAL ASSETS | C28: 0 | E28: 0 | G28: 0
B29: 1 Investments in related parties (acc. 261 - 2961) | C29: 0 | E29: 0 | G29: 0
B30: 2 Loans granted to related parties (acc. 2671 + 2671 - 2964) | C30: 0 | E30: 0 | G30: 0
B31: 3 Equity investment (acc. 262 + 263 - 2962) | C31: 0 | E31: 0 | G31: 0
B32: 4 Loans granted to associated entities and jointly controlled entities (acc. 2673 + 2674 - 2965) | C32: 0 | E32: 0 | G32: 0
B33: 5 Other fixed assets (acc. 265 + 266 - 2963) | C33: 0 | E33: 0 | G33: 0
B34: 6 Other loans (acc. 2675* + 2676* + 2677 + 2678* + 2679* - 2966* - 2968*) | C34: 2809.4565 | D34: =$C34/$C$66 -> 0.00013316385 | E34: 10378.693 | F34: =$E34/$E$66 -> 0.00055178678 | G34: 10077.805 | H34: =$G34/$G$66 -> 0.00065460991
B35: TOTAL (row 18 to 23) | C35: 2809.4565 | D35: =$C35/$C$66 -> 0.00013316385 | E35: 10378.693 | F35: =$E35/$E$66 -> 0.00055178678 | G35: 10077.805 | H35: =$G35/$G$66 -> 0.00065460991
B37: TOTAL NON-CURRENT ASSETS (row 07+17+24) | C37: 9583463.9 | D37: =$C37/$C$66 -> 0.45424122 | E37: 7426477.8 | F37: =$E37/$E$66 -> 0.39483122 | G37: 5209763.8 | H37: =$G37/$G$66 -> 0.33840337
B39: CURRENT ASSETS | C39: 0 | E39: 0 | G39: 0
B40: I. INVENTORIES | C40: 0 | E40: 0 | G40: 0
B41: 1 Raw materials and consumables (acc. 301 + 302 + 303 +/- 308 +321 + 322 + 323 + 328 + 351 + 358 + 381 +/- 388 - 391 - 392 - 3951 - 3958 - 398) | C41: 144370.78 | D41: =$C41/$C$66 -> 0.0068429496 | E41: 133187.54 | F41: =$E41/$E$66 -> 0.0070809609 | G41: 141271.21 | H41: =$G41/$G$66 -> 0.0091763572
B42: 2 Production in progress (acc. 331 + 332 +341 +/- 348* - 393 - 3941 - 3952) | C42: 0 | E42: 0 | G42: 0
B43: 3 Finished goods and commodities (acc. 327 + 345 + 346 + 347 +/- 348* + 354 + 356 + 357 + 361 + 326 +/- 368 + 371 +/- 378 - 3945 - 3946 - 3947 - 3953 - 3954 - 3955 - 3956 - 3957 - 396 - 397 - din ct 4428) | C43: 0 | E43: 0 | G43: 0
B44: 4 Advances (acc. 4091 - 4901) | C44: 0 | E44: 0 | G44: 0
B45: TOTAL (row 26 to 29) | C45: 144370.78 | D45: =$C45/$C$66 -> 0.0068429496 | E45: 133187.54 | F45: =$E45/$E$66 -> 0.0070809609 | G45: 141271.21 | H45: =$G45/$G$66 -> 0.0091763572
B46: II. RECEIVABLES | C46: 0 | E46: 0 | G46: 0
B47: 1 Trade receivables (acc. 2675* + 2676* + 2678* + 2679* - 2966* - 2968* + 4092 + 411 + 413 + 418 - 4902 - 491) | C47: 6410442.7 | D47: =$C47/$C$66 -> 0.30384497 | E47: 5777055.7 | F47: =$E47/$E$66 -> 0.30713913 | G47: 5051499.2 | H47: =$G47/$G$66 -> 0.32812319
B48: 2 Receivables from affiliated entities (acc. 451** - 495*) | C48: 508999.8 | D48: =$C48/$C$66 -> 0.024125795 | E48: 3977135.3 | F48: =$E48/$E$66 -> 0.21144575 | G48: 1379248.7 | H48: =$G48/$G$66 -> 0.089589936
B49: 3 Receivables from associated entities and jointly controlled entities (acc. 453** - 495*) | C49: 0 | E49: 0 | G49: 0
B50: 4 Other receivables (ct 425 + 4282 + 431** + 436**+437** + 4382 + 441** + 4424 + din ct 4428** + 444** + 445 + 446 ** + 447** + 4482 + 4582 + 4662 + 461 + 473** - 496 + 5187) | C50: 982636.69 | D50: =$C50/$C$66 -> 0.046575445 | E50: 234281.61 | F50: =$E50/$E$66 -> 0.012455662 | G50: 322052.87 | H50: =$G50/$G$66 -> 0.02091914
B51: 5 Subscribed and not paid capital (acc. 456 - 495*) | C51: 0 | E51: 0 | G51: 0
B52: 6 Dividends receivables for interim distributions (acc. 463) | C52: 0 | E52: 0 | G52: 0
B53: TOTAL (row 31 to 36) | C53: 7902079.2 | D53: =$C53/$C$66 -> 0.37454621 | E53: 9988472.6 | F53: =$E53/$E$66 -> 0.53104055 | G53: 6752800.8 | H53: =$G53/$G$66 -> 0.43863227
B54: III. SHORT TERM INVESTMENTS | C54: 0 | E54: 0 | G54: 0
B55: 1 Shares owned in affiliated entities (acc. 501 - 591) | C55: 0 | E55: 0 | G55: 0
B56: 2 Other short-term investments (acc. 505 + 506 + 507 + din ct 508 - 595 - 596 - 598 + 5113 + 5114) | C56: 0 | E56: 0 | G56: 0
B57: TOTAL (row 38 to 39) | C57: 0 | E57: 0 | G57: 0
B58: IV PETTY CASH AND BANK ACCOUNTS (acc. 508 + ct 5112 + 512 + 531 + 532 + 541 + 542) | C58: 3309318 | D58: =$C58/$C$66 -> 0.15685651 | E58: 1087263.7 | F58: =$E58/$E$66 -> 0.057804746 | G58: 1272354.3 | H58: =$G58/$G$66 -> 0.082646545
B60: TOTAL CURRENT ASSETS (row 30+37+40+41) | C60: 11355768 | D60: =$C60/$C$66 -> 0.53824567 | E60: 11208924 | F60: =$E60/$E$66 -> 0.59592626 | G60: 9990197.2 | H60: =$G60/$G$66 -> 0.64891932 | J60: =SUM(C58,C53,C45) -> 11355768 | K60: =SUM(D58,D53,D45) -> 0.53824567 | L60: =SUM(E58,E53,E45) -> 11208924 | M60: =SUM(F58,F53,F45) -> 0.59592626 | N60: =SUM(G58,G53,G45) -> 8166426.3
B62: PREPAYMENTS (acc 471 + 474) (row 44 + 45) | C62: 158509.6 | D62: =$C62/$C$66 -> 0.0075131074 | E62: 173844.82 | F62: =$E62/$E$66 -> 0.0092425194 | G62: 195168.88 | H62: =$G62/$G$66 -> 0.012677313
B63: Amounts to be resumed in a period of up to one year (acc. 471* + 474) | C63: 158509.6 | D63: =$C63/$C$66 -> 0.0075131074 | E63: 173844.82 | F63: =$E63/$E$66 -> 0.0092425194 | G63: 0 | H63: =$G63/$G$66 -> 0
B64: Amounts to be resumed in a period of more than one year (acc. 471* + 474) | C64: 0 | E64: 0 | G64: 0
B66: Total Assets | C66: =C62+C60+C37 -> 21097742 | D66: 1 | E66: =E62+E60+E37 -> 18809246 | F66: 1 | G66: =G62+G60+G37 -> 15395130 | H66: 1
B67: Growth in % | E67: =E66/C66-1 -> -0.1084711 | G67: =G66/E66-1 -> -0.18151267
B68: Payables: Amounts to be paid in a period of up to one year | C68: 0 | E68: 0 | G68: 0
B69: 1 Loans from the issue of bonds; the issue of convertible bonds shall be disclosed separately (acc. 161 +1681 - 169) | C69: 0 | E69: 0 | G69: 0
B70: 2 Amounts owed to credit institutions (acc. 1621 + 1622 + 1624 + 1625 + 1627 + 1682 + 5191 + 5192 + 5198) | C70: 3183827.8 | D70: =$C70/$C$143 -> 0.15090847 | E70: 3054053.5 | F70: =$E70/$E$143 -> 0.16236979 | G70: 3063751.7 | H70: =$G70/$G$143 -> 0.19900785
B71: 3 Advances received for the orders (acc. 419) | C71: 11448.98 | D71: =$C71/$C$143 -> 0.00054266375 | E71: 12302.915 | F71: =$E71/$E$143 -> 0.00065408864 | G71: 9797.5472 | H71: =$G71/$G$143 -> 0.00063640562
B72: 4 Trade payables - suppliers (acc. 401 + 404 + 408) | C72: 3341737.7 | D72: =$C72/$C$143 -> 0.15839315 | E72: 3288470.6 | F72: =$E72/$E$143 -> 0.17483266 | G72: 2804518.9 | H72: =$G72/$G$143 -> 0.18216923
B73: 5 Bills of exchange payable (acc. 403 + 405) | C73: 0 | D73: =$C73/$C$143 -> 0 | E73: 0 | F73: =$E73/$E$143 -> 0 | G73: 0
B74: 6 Amounts owed to affiliated entities (acc. 1661 + 1685 + 2691 + 451***) | C74: 0 | D74: =$C74/$C$143 -> 0 | E74: 0 | F74: =$E74/$E$143 -> 0 | G74: 0
B75: 7 Amounts owed to associated entities and jointly controlled entities (acc. 1663 + 1686 + 2692 + 2693 + 453***) | C75: 899709.03 | D75: =$C75/$C$143 -> 0.042644803 | E75: 0 | F75: =$E75/$E$143 -> 0 | G75: 0
B76: 8 Other debts, including fiscal debts and debts related to social securities (acc. 1623 + 1626 + 167 + 1687 + 2695 + 421 + 423 + 424 + 426 + 427 + 4281 + 431*** + 436*** + 437*** + 4381 + 441*** + 4423 + 4428*** + 444*** + 446*** + 447*** + 4481 + 455 + 456*** + 457 + 4581 + 462 + 4661 + 467 + 473*** + 509 + 5186 + 5193 + 5194 + 5195 + 5196 + 5197) | C76: 868891.09 | D76: =$C76/$C$143 -> 0.04118408 | E76: 890634.77 | F76: =$E76/$E$143 -> 0.047350901 | G76: 849510.45 | H76: =$G76/$G$143 -> 0.055180467
B77: TOTAL (row 46 to 53) | C77: 8305614.7 | D77: =$C77/$C$143 -> 0.39367316 | E77: 7245461.7 | F77: =$E77/$E$143 -> 0.38520744 | G77: 6727578.6 | H77: =$G77/$G$143 -> 0.43699395
B79: E NET CURRENT ASSETS/NET CURRENT LIABILITIES (row 42 + 44 - 54 - 71 - 74 - 77) | C79: 3208663 | D79: =$C79/$C$143 -> 0.15208561 | E79: 4137306.9 | F79: =$E79/$E$143 -> 0.21996133 | G79: 3457787.5 | H79: =$G79/$G$143 -> 0.22460268
B81: F TOTAL ASSETS MINUS CURRENT LIABILITIES (row 25 + 45 + 55) | C81: 12792127 | D81: =$C81/$C$143 -> 0.60632683 | E81: 11563785 | F81: =$E81/$E$143 -> 0.61479255 | G81: 8667551.3 | H81: =$G81/$G$143 -> 0.56300605
B83: Payables: Amounts to be paid in a period of more than one year | C83: 0 | E83: 0 | G83: 0
B84: 1 Loans from the issue of bonds; the issue of convertible bonds shall be disclosed separately (acc. 161 + 1681 - 169) | C84: 0 | E84: 0 | G84: 0
B85: 2 Amounts owed to credit institutions (acc. 1621 + 1622 + 1624 + 1625 + 1627 + 1682 + 5191 + 5192 + 5198) | C85: 10841985 | D85: =$C85/$C$143 -> 0.51389313 | E85: 8609126.6 | F85: =$E85/$E$143 -> 0.45770715 | G85: 5545072.6 | H85: =$G85/$G$143 -> 0.36018355
B86: 3 Advances received for the orders (acc. 419) | C86: 0 | E86: 0 | G86: 0
B87: 4 Trade payables - suppliers (acc. 401 + 404 + 408) | C87: 0 | E87: 0 | G87: 0
B88: 5 Bills of exchange payable (acc. 403 + 405) | C88: 0 | E88: 0 | G88: 0
B89: 6 Amounts owed to affiliated entities (acc. 1661 + 1685 + 2691 + 451***) | C89: 0 | E89: 0 | G89: 0
B90: 7 Amounts owed to associated entities and jointly controlled entities (acc. 1663 + 1686 + 2692 + 2693 + 453***) | C90: 0 | E90: 0 | G90: 0
B91: 8 Other debts, including fiscal debts and debts related to social securities (acc. 1623 + 1626 + 167 + 1687 + 2695 + 421 + 423 + 424 + 426 + 427 + 4281 + 431*** + 436***+437*** + 4381 + 441*** + 4423 + 4428*** + 444*** + 446*** + 447*** + 4481 + 455 + 456*** + 4581 + 462 + 4661 + 473*** + 509 + 5186 + 5193 + 5194 + 5195 + 5196 + 5197) | C91: 342841.79 | D91: =$C91/$C$143 -> 0.016250165 | E91: 403857.49 | F91: =$E91/$E$143 -> 0.021471221 | G91: 211459.79 | H91: =$G91/$G$143 -> 0.013735499
B92: TOTAL (row 57 to 64) | C92: 11184826 | D92: =$C92/$C$143 -> 0.5301433 | E92: 9012984.1 | F92: =$E92/$E$143 -> 0.47917837 | G92: 5756532.4 | H92: =$G92/$G$143 -> 0.37391905
B94: PROVISIONS | C94: 0 | E94: 0 | G94: 0
B95: 1 Provisions for employee benefits (acc. 1515 + 1517) | C95: 0 | E95: 0 | G95: 0
B96: 2 Provisions for taxes (acc. 1516) | C96: 0 | E96: 0 | G96: 0
B97: 3 Other provisions (acc. 1511 + 1512 + 1513 + 1514 + 1518) | C97: 0 | E97: 0 | G97: 0
B98: TOTAL PROVISIONS (row 66, 67 and 68 ) | C98: 0 | E98: 0 | G98: 0
B99: INCOME IN ADVANCE | C99: 0 | E99: 0 | G99: 0
B100: 1 Investment subsidies (acc. 475) (row 71 + 72), out of which: | C100: 0 | E100: 0 | G100: 0
B101: Amounts to be resumed in a period of up to one year (from acc. 475*) | C101: 0 | E101: 0 | G101: 0
B102: Amounts to be resumed in a period of more than one year (from acc. 475*) | C102: 0 | E102: 0 | G102: 0
B103: 2 Deferred income (acc. 472) - total (row 74 + 75), out of which: | C103: 0 | E103: 0 | G103: 0
B104: Amounts to be resumed in a period of up to one year (from acc. 472*) | C104: 0 | E104: 0 | G104: 0
B105: Amounts to be resumed in a period of more than one year (from acc. 472*) | C105: 0 | E105: 0 | G105: 0
... B111: CAPITAL AND RESERVES | C111: 0 | E111: 0 | G111: 0
B112: 1 Subscribed and paid up share capital (acc. 1012) | C112: 2020.6102 | D112: =$C112/$C$143 -> 9.5773768e-05 | E112: 2010.0503 | F112: =$E112/$E$143 -> 0.00010686501 | G112: 2010.4544 | H112: =$G112/$G$143 -> 0.00013059028
B113: 2 Subscribed and not paid share capital (acc. 1011) | C113: 0 | E113: 0 | G113: 0
B114: 3 Patrimony (autonomus companies) (acc. 1015) | C114: 0 | E114: 0 | G114: 0
B115: 4 Patrimony of national institutions for research and development (acc. 1018) | C115: 0 | E115: 0 | G115: 0
B116: 5 Other equity elements (acc. 1031) | C116: 0 | E116: 0 | G116: 0
...

Sheet P&L 2022-2024 (2)
B2: VioTrans Group SRL | C2: Source: https://www.ecb.europa.eu/stats/policy_and_exchange_rates/euro_reference_exchange_rates/html/eurofxref-graph-ron.de.html
C3: EUR vs. RON | E3: EUR vs. RON | G3: EUR vs. RON
B4: In € | C4: 46021 | E4: 45655 | G4: 45657
C5: 4.949 | E5: 4.975 | G5: 4.974
B7: No. Description | C7: for the period ended December 31, 2022 | E7: for the period ended December 31, 2023 | G7: for the period ended December 31, 2024
B8: 1. Net turnover | C8: =SUM(C11:C14) -> 38216486 | D8: =C8/C24 -> 0.9884008 | E8: 37396294 | F8: =E8/E24 -> 0.98546718 | G8: =SUM(G11:G14) -> 34006909 | H8: =G8/G24 -> 0.98263516
B9: - out of which net turnover for the main activity | C9: 0 | E9: 0 | G9: 32096156
B10: - out of which, the net turnover achieved from operations carried out on national territory | C10: 0 | E10: 0 | G10: 341506.25
B11: Sales of goods | C11: 36069540 | D11: =C11/C24 -> 0.93287391 | E11: 0 | F11: =E11/E24 -> 0 | G11: 32197889 | H11: =G11/G24 -> 0.93036324
B12: Sales of merchandise | C12: 2146945.6 | D12: =C12/C24 -> 0.055526895 | E12: 0 | F12: =E12/E24 -> 0 | G12: 1809019.5 | H12: =G12/G24 -> 0.052271913
B13: Discounts granted | C13: 0 | E13: 0 | G13: 0
B14: Revenue from operating subsidies related to the turnover | C14: 0 | E14: 0 | G14: 0
B15: 2. Revenue related to the cost of the work in progress | C15: 0 | E15: 0 | G15: 0
B16: Revenue related to the cost of the work in progress | C16: 0 | E16: 0 | G16: 0
B17: 3. Income from production of tangible and intangible assets | C17: 0 | E17: 0 | G17: 0
B18: 4. Income from the revaluation of tangible assets | C18: 0 | E18: 0 | G18: 0
B19: 5. Income from production of real estate investments | C19: 0 | E19: 0 | G19: 0
B20: 6. Income from operating subsidies | C20: 0 | E20: 0 | G20: 0
B21: 7. Other operating income | C21: 448482.52 | D21: =C21/C24 -> 0.011599195 | E21: 551488.24 | F21: =E21/E24 -> 0.014532819 | G21: 600960.19 | H21: =G21/G24 -> 0.017364843
B22: - out of which, income from investment subsidies | C22: 6159.6282 | D22: =C22/C24 -> 0.00015930773 | E22: 0 | G22: 0
B23: - out of which, income from negative goodwill | C23: 0 | E23: 0 | G23: 0
B24: OPERATING INCOME – TOTAL | C24: =SUM(C21,C8) -> 38664968 | D24: =SUM(D11:D23) -> 1.0001593 | E24: =SUM(E21,E8) -> 37947783 | F24: =SUM(F11:F23) -> 0.014532819 | G24: =SUM(G21,G8) -> 34607869 | H24: =SUM(H11:H23) -> 1
B25: Growth in % | E25: =E24/C24-1 -> -0.018548728 | G25: =G24/E24-1 -> -0.088013411
B26: 8. a) Expenses related to raw materials and consumables | C26: 6764286.9 | D26: =C$26/$C$24 -> 0.17494614 | E26: 6514435.2 | F26: =E$26/$E$24 -> 0.1716684 | G26: 5768370.5 | H26: =G$26/$G$24 -> 0.16667801
B27: Other material expenses | C27: 30171.752 | D27: =$C27/$C$24 -> 0.0007803382 | E27: 33208.442 | F27: =$E27/$E$24 -> 0.0008751089 | G27: 21910.334 | H27: =$G27/$G$24 -> 0.00063310266
B28: b) Other external expenses (power and water supply) | C28: 86376.44 | D28: =$C28/$C$24 -> 0.0022339716 | E28: 61133.065 | F28: =$E28/$E$24 -> 0.0016109786 | G28: 40715.32 | H28: =$G28/$G$24 -> 0.0011764758
B29: - out of which, expenses with power consumption | C29: 84990.099 | D29: =$C29/$C$24 -> 0.0021981163 | E29: 58890.452 | F29: =$E29/$E$24 -> 0.0015518813 | G29: 37208.484 | H29: =$G29/$G$24 -> 0.0010751452
B30: - out of which, expenses with natural gas consumption | C30: 0 | E30: 0 | G30: 0
B31: c) Merchandise expenses | C31: 2145422.1 | D31: =$C31/$C$24 -> 0.055487491 | E31: 1748810.5 | F31: =$E31/$E$24 -> 0.046084655 | G31: 1808855.6 | H31: =$G31/$G$24 -> 0.052267178
B32: Commercial discounts received | C32: 0 | E32: 0 | G32: 0
B33: 9. Personnel expenses | C33: =SUM(C34:C35) -> 3420668.4 | D33: =$C33/$C$24 -> 0.088469448 | E33: =SUM(E34:E35) -> 4168543.1 | F33: =$E33/$E$24 -> 0.10984945 | G33: =SUM(G34:G35) -> 4283540.6 | H33: =$G33/$G$24 -> 0.1237736
B34: a) Salaries and allowance | C34: 3347551.6 | D34: =$C34/$C$24 -> 0.086578413 | E34: 4079188.7 | F34: =$E34/$E$24 -> 0.10749479 | G34: 4188603.7 | H34: =$G34/$G$24 -> 0.12103039
B35: b) Social security | C35: 73116.791 | D35: =$C35/$C$24 -> 0.0018910346 | E35: 89354.372 | F35: =$E35/$E$24 -> 0.0023546665 | G35: 94936.872 | H35: =$G35/$G$24 -> 0.0027432164
B36: 10. a) Value adjustments regarding tangible and intangible assets | C36: =SUM(C37:C39) -> 2860043.2 | D36: =$C36/$C$24 -> 0.073969884 | E36: =SUM(E37:E39) -> 2910385.1 | F36: =$E36/$E$24 -> 0.076694472 | G36: =SUM(G37:G39) -> 2502104.1 | H36: =$G36/$G$24 -> 0.072298706
B37: a. 1) Expenses with depreciation and amortisation | C37: 2860043.2 | D37: =$C37/$C$24 -> 0.073969884 | E37: 2910385.1 | F37: =$E37/$E$24 -> 0.076694472 | G37: 2502104.1 | H37: =$G37/$G$24 -> 0.072298706
B38: a. 2) Other expenses | C38: 0 | E38: 0 | G38: 0
B39: a. 3) Income | C39: 0 | E39: 0 | G39: 0
B40: 10. b) Value adjustments regarding current assets | C40: =C41-C42 -> 1497.2722 | D40: =$C40/$C$24 -> 3.8724257e-05 | E40: =E41-E42 -> -6619.2965 | F40: =$E40/$E$24 -> -0.00017443171 | G40: =G41-G42 -> 36502.01 | H40: =$G40/$G$24 -> 0.0010547315
B41: b. 1) Expenses | C41: 60289.351 | D41: =$C41/$C$24 -> 0.0015592758 | E41: 8057.2864 | F41: =$E41/$E$24 -> 0.00021232562 | G41: 48636.711 | H41: =$G41/$G$24 -> 0.0014053657
B42: b. 2) Income | C42: 58792.079 | D42: =$C42/$C$24 -> 0.0015205516 | E42: 14676.583 | F42: =$E42/$E$24 -> 0.00038675733 | G42: 12134.7 | H42: =$G42/$G$24 -> 0.00035063414
B43: 11. Other operating expenses | C43: =SUM(C44:C59)-C50-C52-C54-C45 -> 20860357 | D43: =SUM(D44:D59) -> 0.53951993 | E43: =SUM(E44:E59)-E50-E52-E54-E45 -> 20773838 | F43: =$E43/$E$24 -> 0.5474322 | G43: =SUM(G44:G59)-G50-G52-G54-G45 -> 19593999 | H43: =$G43/$G$24 -> 0.56617178
B44: 11.1. External services expenses | C44: 20609084 | D44: =$C44/$C$24 -> 0.53301695 | E44: 20097555 | F44: =$E44/$E$24 -> 0.52961078 | G44: 19154840 | H44: =$G44/$G$24 -> 0.55348221
B45: 11.2.Expenses with Royalties, management leases and rental | C45: 164.07355 | D45: =$C45/$C$24 -> 4.2434678e-06 | E45: 35171.457 | F45: =$E45/$E$24 -> 0.00092683828 | G45: 85481.303 | H45: =$G45/$G$24 -> 0.0024699962
B46: - Expenses with Royalties | C46: 0 | E46: 0 | G46: 0
B47: - Expenses with Management leases | C47: 0 | E47: 0 | G47: 0
B48: - Expenses with Rent expenses | C48: 164.07355 | D48: =$C48/$C$24 -> 4.2434678e-06 | E48: 35171.457 | F48: =$E48/$E$24 -> 0.00092683828 | G48: 85481.303 | H48: =$G48/$G$24 -> 0.0024699962
B49: 11.2.Expenses with Intellectual property rights | C49: 0 | E49: 0 | G49: 0
B50: - of which, expenses related to affiliates | C50: 0 | E50: 0 | G50: 0
B51: 11.4. Expenses with management | C51: 0 | E51: 0 | G51: 0
B52: - of which, expenses related to affiliates | C52: 0 | E52: 0 | G52: 0
B53: 11.5. Expenses with consulting | C53: 0 | E53: 0 | G53: 0
B54: - of which, expenses related to affiliates | C54: 0 | E54: 0 | G54: 0
B55: 11.6. Expenses with other taxes, charges and similar expenses; Transfers and contributions owed based on special acts of legislation | C55: 101415.24 | D55: =$C55/$C$24 -> 0.002622923 | E55: 107909.35 | F55: =$E55/$E$24 -> 0.0028436272 | G55: 126989.14 | H55: =$G55/$G$24 -> 0.003669372
B56: 11.7. Expenses with environmental protection | C56: 0 | E56: 0 | G56: 0
B57: 11.8. Expenses related to revaluation of tangible assets | C57: 0 | E57: 0 | G57: 0
B58: 11.9. Expenses related to natural disasters and other similar events | C58: 0 | E58: 0 | G58: 0
B59: 11.10. Other expenses | C59: 149693.88 | D59: =$C59/$C$24 -> 0.0038715634 | E59: 533202.61 | F59: =$E59/$E$24 -> 0.014050956 | G59: 226688.58 | H59: =$G59/$G$24 -> 0.0065502034
B60: 12. Adjustments regarding the provisions | C60: 0 | E60: 0 | G60: 0 | H60: =$G60/$G$24 -> 0
B61: - Expenses | C61: 0 | E61: 0 | G61: 0
B62: - Income | C62: 0 | E62: 0 | G62: 0
B63: OPERATING EXPENSES – TOTAL | C63: =C26+C27+C28+C31+C32+C33+C36+C40+C43+C60 -> 36168823 | D63: =$C63/$C$24 -> 0.93544168 | E63: =E26+E27+E28+E31+E32+E33+E36+E40+E43+E60 -> 36203734 | F63: =$E63/$E$24 -> 0.95404083 | G63: =G26+G27+G28+G31+G32+G33+G36+G40+G43+G60 -> 34055997 | H63: =$G63/$G$24 -> 0.98405358
B64: OPERATING PROFIT OR LOSS | C64: 0 | E64: 0 | G64: 0
B65: - Profit | C65: =IF(C24>C63,C24-C63,0) -> 2496145.5 | D65: =$C65/$C$24 -> 0.064558322 | E65: =IF(E24>E63,E24-E63,0) -> 1744048.4 | F65: =$E65/$E$24 -> 0.045959166 | G65: =IF(G24>G63,G24-G63,0) -> 551871.53 | H65: =$G65/$G$24 -> 0.015946418
B66: - Loss | C66: 0 | E66: 0 | G66: 0
B67: 13. Income from participating interests | C67: 0 | E67: 0 | G67: 0
B68: - of which, income from affiliates | C68: 0 | E68: 0 | G68: 0
B69: Growth in % | E69: =E65/C65-1 -> -0.30130337 | G69: =G65/E65-1 -> -0.68356869
B70: 14. Interest income | C70: 73234.189 | D70: =$C70/$C$24 -> 0.0018940708 | E70: 232947.54 | F70: =$E70/$E$24 -> 0.0061386337 | G70: 228424.41 | H70: =$G70/$G$24 -> 0.0066003604
B71: - of which, income from affiliates | C71: 21972.396 | D71: =$C71/$C$24 -> 0.00056827659 | E71: 209530.25 | F71: =$E71/$E$24 -> 0.0055215414 | G71: 195674.11 | H71: =$G71/$G$24 -> 0.0056540351
B72: 15. Income from operating subsidies for interest payable | C72: 0 | E72: 0 | G72: 0
B73: 16. Other financial income | C73: 506588.4 | D73: =$C73/$C$24 -> 0.013102 | E73: 541952.96 | F73: =$E73/$E$24 -> 0.014281545 | G73: 182803.38 | H73: =$G73/$G$24 -> 0.0052821334
B74: - of which, income from financial assets | C74: 0 | E74: 0 | G74: 0
B75: FINANCIAL INCOME – TOTAL | C75: =SUM(C67,C72,C73,C70) -> 579822.59 | D75: =$C75/$C$24 -> 0.01499607 | E75: =SUM(E67,E72,E73,E70) -> 774900.5 | F75: =$E75/$E$24 -> 0.020420179 | G75: =SUM(G67,G72,G73,G70) -> 411227.78 | H75: =$G75/$G$24 -> 0.011882494
B76: 17. Value adjustments regarding the financial assets and financial investments held as current assets | C76: 0 | E76: 0 | G76: 0 | H76: =$G76/$G$24 -> 0
B77: Expenses | C77: 0 | E77: 0 | G77: 0
B78: Income | C78: 0 | E78: 0 | G78: 0
B79: 18. Interest expenses | C79: 281040.01 | D79: =$C79/$C$24 -> 0.0072685953 | E79: 407228.74 | F79: =$E79/$E$24 -> 0.010731292 | G79: 333678.53 | H79: =$G79/$G$24 -> 0.0096416954
B80: - of which, expenses related to affiliates | C80: 465.34653 | D80: =$C80/$C$24 -> 1.2035353e-05 | E80: 0 | G80: 0
B81: 19. Other financial expenses | C81: 455423.12 | D81: =$C81/$C$24 -> 0.011778701 | E81: 549921.01 | F81: =$E81/$E$24 -> 0.014491519 | G81: 137559.11 | H81: =$G81/$G$24 -> 0.0039747928
B82: FINANCIAL EXPENSES – TOTAL | C82: =SUM(C81,C79,C76) -> 736463.12 | D82: =$C82/$C$24 -> 0.019047297 | E82: =SUM(E81,E79,E76) -> 957149.75 | F82: =$E82/$E$24 -> 0.025222811 | G82: =SUM(G81,G79,G76) -> 471237.64 | H82: =$G82/$G$24 -> 0.013616488
B83: - Profit | C83: 0 | E83: 0 | G83: 0
B84: - Loss | C84: 156640.53 | D84: =$C84/$C$24 -> 0.0040512262 | E84: 182249.25 | F84: =$E84/$E$24 -> 0.0048026323 | G84: 60009.851 | H84: =$G84/$G$24 -> 0.0017339944
B85: TOTAL INCOME | C85: =C24+C75 -> 39244791 | D85: =$C85/$C$24 -> 1.0149961 | E85: =E24+E75 -> 38722683 | F85: =$E85/$E$24 -> 1.0204202 | G85: =G24+G75 -> 35019097 | H85: =$G85/$G$24 -> 1.0118825
B86: TOTAL EXPENSES | C86: =C63+C82 -> 36905286 | D86: =$C86/$C$24 -> 0.95448897 | E86: =E63+E82 -> 37160884 | F86: =$E86/$E$24 -> 0.97926364 | G86: =G63+G82 -> 34527235 | H86: =$G86/$G$24 -> 0.99767007
B87: GROSS PROFIT OR LOSS | C87: 0 | E87: 0 | G87: 0
B88: - Profit | C88: 2339505 | D88: =$C88/$C$24 -> 0.060507096 | E88: 1561799.2 | F88: =$E88/$E$24 -> 0.041156534 | G88: 491861.68 | H88: =$G88/$G$24 -> 0.014212423
B89: - Loss | C89: 0 | E89: 0 | G89: 0
B90: 20. Income Tax | C90: 364367.75 | D90: =$C90/$C$24 -> 0.0094237178 | E90: 270599.8 | F90: =$E90/$E$24 -> 0.0071308462 | G90: 132156.41 | H90: =$G90/$G$24 -> 0.0038186811
C91: 0 | E91: 0 | G91: 0
B92: 21. Expenses with income tax, including minimum turnover tax, resulting from income tax settlements in the tax group | C92: 0 | E92: 0 | G92: 0
C93: 0 | E93: 0 | G93: 0
B94: 22. Income from income tax, including minimum turnover tax, resulting from income tax settlements in the tax group | C94: 0 | E94: 0 | G94: 0
C95: 0 | E95: 0 | G95: 0
B96: 23. Expenses with income tax at the level of the minimum turnover tax | C96: 0 | E96: 0 | G96: 0
B97: 24. Other taxes not included in the captions above | C97: 0 | E97: 0 | G97: 0
B98: NET PROFIT OR LOSS FOR THE REPORTING PERIOD - Profit | C98: =IF(C88-C90-C96-C97>0,C88-C90-C96-C97) -> 1975137.2 | D98: =$C98/$C$24 -> 0.051083378 | E98: =IF(E88-E90-E96-E97>0,E88-E90-E96-E97) -> 1291199.4 | F98: =$E98/$E$24 -> 0.034025688 | G98: =IF(G88-G90-G96-G97>0,G88-G90-G96-G97) -> 359705.27 | H98: =$G98/$G$24 -> 0.010393742
B99: - Loss | C99: 0 | E99: 0 | G99: 0
B100: Growth in % | E100: =E98/C98-1 -> -0.34627357 | G100: =G98/E98-1 -> -0.72141772
B104: EBIT | C104: =C98+C90+C82-C75 -> 2496145.5 | E104: =E98+E90+E82-E75 -> 1744048.4 | G104: =G98+G90+G82-G75 -> 551871.53
C105: =C104/C24 -> 0.064558322 | E105: =E104/E24 -> 0.045959166 | G105: =G104/G24 -> 0.015946418
...

Sheet Balance Sheet 2022-2024 (2)
B2: VioTrans Group SRL | C2: Source: https://www.ecb.europa.eu/stats/policy_and_exchange_rates/euro_reference_exchange_rates/html/eurofxref-graph-ron.de.html
C3: EUR vs. RON | E3: EUR vs. RON | G3: EUR vs. RON
B4: In € | C4: 46021 | E4: 45655 | G4: 45657
C5: 4.949 | E5: 4.975 | G5: 4.974
B7: No. Description | C7: as at December 31, 2022 | E7: as at December 31, 2023 | G7: as at December 31, 2024
B8: NON-CURRENT ASSETS
B9: I. INTANGIBLE ASSETS
B10: 1 Set-up expenses | C10: 0 | E10: 0 | G10: 0
B11: 2 Development expenses | C11: 0 | E11: 0 | G11: 0
B12: 3 Concessions, patents, licenses, trademarks, similar rights and assets and other intangible assets | C12: 4011.3154 | D12: =C12/C37 -> 0.00041856634 | E12: 25585.528 | F12: =E12/E37 -> 0.0034451766 | G12: 19983.514 | H12: =G12/G37 -> 0.0038357813
B13: 4 Goodwill | C13: 0 | E13: 0 | G13: 0
B14: 5 Intangible exploration assets and evaluation of mineral resources | C14: 0 | E14: 0 | G14: 0
B15: 6 Advances | C15: 0 | E15: 0 | G15: 0
B16: TOTAL | C16: =SUM(C10:C15) -> 4011.3154 | D16: =C16/C66 -> 0.00019013009 | E16: =SUM(E10:E15) -> 25585.528 | F16: =E16/E66 -> 0.0013602633 | G16: =SUM(G10:G15) -> 19983.514 | H16: =G16/G66 -> 0.0012980413
B17: II. TANGIBLE ASSETS | C17: 0 | E17: 0 | G17: 0
B18: 1 Land and buildings | C18: 1523198.8 | D18: =$C18/$C$66 -> 0.072197246 | E18: 1452865.5 | F18: =$E18/$E$66 -> 0.077242091 | G18: 1370667.7 | H18: =$G18/$G$66 -> 0.08903255
B19: 2 Installations and machinery | C19: 7850724.8 | D19: =$C19/$C$66 -> 0.37211209 | E19: 5860386.3 | F19: =$E19/$E$66 -> 0.31156944 | G19: 3554068 | H19: =$G19/$G$66 -> 0.23085664
B20: 3 Other installations, machines and furniture | C20: 76867.448 | D20: =$C20/$C$66 -> 0.003643397 | E20: 77261.709 | F20: =$E20/$E$66 -> 0.0041076451 | G20: 154964.82 | H20: =$G20/$G$66 -> 0.010065834
B21: 4 Investment property | C21: 0 | E21: 0 | G21: 0
B22: 5 Tangible assets in progress | C22: 4992.5237 | D22: =$C22/$C$66 -> 0.00023663783 | E22: 0 | G22: 0
B23: 6 Investment property in progress | C23: 0 | E23: 0 | G23: 0
B24: 7 Tangible assets for exploration and valuation of mineral resources | C24: 0 | E24: 0 | G24: 0
B25: 8 Productive biological assets | C25: 0 | E25: 0 | G25: 0
B26: 9 Advances | C26: 120859.57 | D26: =$C26/$C$66 -> 0.0057285547 | E26: 0 | G26: 100002.01 | H26: =$G26/$G$66 -> 0.0064956913
B27: TOTAL | C27: =SUM(C18:C26) -> 9576643.2 | D27: =$C27/$C$66 -> 0.45391793 | E27: =SUM(E18:E26) -> 7390513.6 | F27: =$E27/$E$66 -> 0.39291917 | G27: =SUM(G18:G26) -> 5179702.5 | H27: =$G27/$G$66 -> 0.33645071
B28: III. FINANCIAL ASSETS | C28: 0 | E28: 0 | G28: 0
B29: 1 Investments in related parties | C29: 0 | E29: 0 | G29: 0
B30: 2 Loans granted to related parties | C30: 0 | E30: 0 | G30: 0
B31: 3 Equity investment | C31: 0 | E31: 0 | G31: 0
B32: 4 Loans granted to associated entities and jointly controlled entities | C32: 0 | E32: 0 | G32: 0
B33: 5 Other fixed assets | C33: 0 | E33: 0 | G33: 0
B34: 6 Other loans | C34: 2809.4565 | D34: =$C34/$C$66 -> 0.00013316385 | E34: 10378.693 | F34: =$E34/$E$66 -> 0.00055178678 | G34: 10077.805 | H34: =$G34/$G$66 -> 0.00065460991
B35: TOTAL | C35: =SUM(C29:C34) -> 2809.4565 | D35: =$C35/$C$66 -> 0.00013316385 | E35: =SUM(E29:E34) -> 10378.693 | F35: =$E35/$E$66 -> 0.00055178678 | G35: =SUM(G29:G34) -> 10077.805 | H35: =$G35/$G$66 -> 0.00065460991
B37: TOTAL NON-CURRENT ASSETS | C37: =SUM(C35,C27,C16) -> 9583463.9 | D37: =$C37/$C$66 -> 0.45424122 | E37: =SUM(E35,E27,E16) -> 7426477.8 | F37: =$E37/$E$66 -> 0.39483122 | G37: =SUM(G35,G27,G16) -> 5209763.8 | H37: =$G37/$G$66 -> 0.33840337
B39: CURRENT ASSETS | C39: 0 | E39: 0 | G39: 0
B40: I. INVENTORIES | C40: 0 | E40: 0 | G40: 0
B41: 1 Raw materials and consumables | C41: 144370.78 | D41: =$C41/$C$66 -> 0.0068429496 | E41: 133187.54 | F41: =$E41/$E$66 -> 0.0070809609 | G41: 141271.21 | H41: =$G41/$G$66 -> 0.0091763572
B42: 2 Production in progress | C42: 0 | E42: 0 | G42: 0
B43: 3 Finished goods and commodities | C43: 0 | E43: 0 | G43: 0
B44: 4 Advances | C44: 0 | E44: 0 | G44: 0
B45: TOTAL | C45: =SUM(C41:C44) -> 144370.78 | D45: =$C45/$C$66 -> 0.0068429496 | E45: =SUM(E41:E44) -> 133187.54 | F45: =$E45/$E$66 -> 0.0070809609 | G45: =SUM(G41:G44) -> 141271.21 | H45: =$G45/$G$66 -> 0.0091763572
B46: II. RECEIVABLES | C46: 0 | E46: 0 | G46: 0
B47: 1 Trade receivables | C47: 6410442.7 | D47: =$C47/$C$66 -> 0.30384497 | E47: 5777055.7 | F47: =$E47/$E$66 -> 0.30713913 | G47: 5051499.2 | H47: =$G47/$G$66 -> 0.32812319
B48: 2 Receivables from affiliated entities | C48: 508999.8 | D48: =$C48/$C$66 -> 0.024125795 | E48: 3977135.3 | F48: =$E48/$E$66 -> 0.21144575 | G48: 1379248.7 | H48: =$G48/$G$66 -> 0.089589936
B49: 3 Receivables from associated entities and jointly controlled entities | C49: 0 | E49: 0 | G49: 0
B50: 4 Other receivables | C50: 982636.69 | D50: =$C50/$C$66 -> 0.046575445 | E50: 234281.61 | F50: =$E50/$E$66 -> 0.012455662 | G50: 322052.87 | H50: =$G50/$G$66 -> 0.02091914
B51: 5 Subscribed and not paid capital | C51: 0 | E51: 0 | G51: 0
B52: 6 Dividends receivables for interim distributions | C52: 0 | E52: 0 | G52: 0
B53: TOTAL | C53: =SUM(C47:C52) -> 7902079.2 | D53: =$C53/$C$66 -> 0.37454621 | E53: =SUM(E47:E52) -> 9988472.6 | F53: =$E53/$E$66 -> 0.53104055 | G53: =SUM(G47:G52) -> 6752800.8 | H53: =$G53/$G$66 -> 0.43863227
B54: III. SHORT TERM INVESTMENTS | C54: 0 | E54: 0 | G54: 0
B55: 1 Shares owned in affiliated entities | C55: 0 | E55: 0 | G55: 0
B56: 2 Other short-term investments | C56: 0 | E56: 0 | G56: 0
B57: TOTAL | C57: 0 | E57: 0 | G57: 0
B58: IV PETTY CASH AND BANK ACCOUNTS | C58: 3309318 | D58: =$C58/$C$66 -> 0.15685651 | E58: 1087263.7 | F58: =$E58/$E$66 -> 0.057804746 | G58: 1272354.3 | H58: =$G58/$G$66 -> 0.082646545 | J58: =G58*G5 -> 6328690.3
B60: TOTAL CURRENT ASSETS | C60: =SUM(C58,C53,C45) -> 11355768 | D60: =$C60/$C$66 -> 0.53824567 | E60: =SUM(E58,E53,E45) -> 11208924 | F60: =$E60/$E$66 -> 0.59592626 | G60: 9990197.2 | H60: =$G60/$G$66 -> 0.64891932 | I60: TCA 2024 nicht verformelt weil Wert nicht aufgeht -> Fehler in Ursprungsdatei
B62: PREPAYMENTS | C62: 158509.6 | D62: =$C62/$C$66 -> 0.0075131074 | E62: 173844.82 | F62: =$E62/$E$66 -> 0.0092425194 | G62: 195168.88 | H62: =$G62/$G$66 -> 0.012677313
B63: Amounts to be resumed in a period of up to one year | C63: 158509.6 | D63: =$C63/$C$66 -> 0.0075131074 | E63: 173844.82 | F63: =$E63/$E$66 -> 0.0092425194 | G63: 0 | H63: =$G63/$G$66 -> 0
B64: Amounts to be resumed in a period of more than one year | C64: 0 | E64: 0 | G64: 0
B66: Total Assets | C66: =SUM(C62,C60,C37) -> 21097742 | D66: 1 | E66: =SUM(E62,E60,E37) -> 18809246 | F66: 1 | G66: =SUM(G62,G60,G37) -> 15395130 | H66: 1
B67: Growth in % | E67: =E66/C66-1 -> -0.1084711 | G67: =G66/E66-1 -> -0.18151267
B68: Payables: Amounts to be paid in a period of up to one year | C68: 0 | E68: 0 | G68: 0
B69: 1 Loans from the issue of bonds; the issue of convertible bonds shall be disclosed separately | C69: 0 | E69: 0 | G69: 0
B70: 2 Amounts owed to credit institutions | C70: 3183827.8 | D70: =$C70/$C$143 -> 0.15090847 | E70: 3054053.5 | F70: =$E70/$E$143 -> 0.16236979 | G70: 3063751.7 | H70: =$G70/$G$143 -> 0.19900785
B71: 3 Advances received for the orders | C71: 11448.98 | D71: =$C71/$C$143 -> 0.00054266376 | E71: 12302.915 | F71: =$E71/$E$143 -> 0.00065408864 | G71: 9797.5472 | H71: =$G71/$G$143 -> 0.00063640562
B72: 4 Trade payables - suppliers | C72: 3341737.7 | D72: =$C72/$C$143 -> 0.15839315 | E72: 3288470.6 | F72: =$E72/$E$143 -> 0.17483266 | G72: 2804518.9 | H72: =$G72/$G$143 -> 0.18216923
B73: 5 Bills of exchange payable | C73: 0 | D73: =$C73/$C$143 -> 0 | E73: 0 | F73: =$E73/$E$143 -> 0 | G73: 0
B74: 6 Amounts owed to affiliated entities | C74: 0 | D74: =$C74/$C$143 -> 0 | E74: 0 | F74: =$E74/$E$143 -> 0 | G74: 0
B75: 7 Amounts owed to associated entities and jointly controlled entities | C75: 899709.03 | D75: =$C75/$C$143 -> 0.042644803 | E75: 0 | F75: =$E75/$E$143 -> 0 | G75: 0
B76: 8 Other debts, including fiscal debts and debts related to social securities | C76: 868891.09 | D76: =$C76/$C$143 -> 0.041184081 | E76: 890634.77 | F76: =$E76/$E$143 -> 0.047350901 | G76: 849510.45 | H76: =$G76/$G$143 -> 0.055180467
B77: TOTAL | C77: =SUM(C69:C76) -> 8305614.7 | D77: =$C77/$C$143 -> 0.39367317 | E77: =SUM(E69:E76) -> 7245461.7 | F77: =$E77/$E$143 -> 0.38520744 | G77: =SUM(G69:G76) -> 6727578.6 | H77: =$G77/$G$143 -> 0.43699395
B79: E NET CURRENT ASSETS/NET CURRENT LIABILITIES | C79: 3208663 | D79: =$C79/$C$143 -> 0.15208561 | E79: 4137306.9 | F79: =$E79/$E$143 -> 0.21996133 | G79: 3457787.5 | H79: =$G79/$G$143 -> 0.22460268
B81: F TOTAL ASSETS MINUS CURRENT LIABILITIES | C81: 12792127 | D81: =$C81/$C$143 -> 0.60632684 | E81: 11563785 | F81: =$E81/$E$143 -> 0.61479255 | G81: 8667551.3 | H81: =$G81/$G$143 -> 0.56300605
B83: Payables: Amounts to be paid in a period of more than one year | C83: 0 | E83: 0 | G83: 0
B84: 1 Loans from the issue of bonds; the issue of convertible bonds shall be disclosed separately | C84: 0 | E84: 0 | G84: 0
B85: 2 Amounts owed to credit institutions | C85: 10841985 | D85: =$C85/$C$143 -> 0.51389314 | E85: 8609126.6 | F85: =$E85/$E$143 -> 0.45770715 | G85: 5545072.6 | H85: =$G85/$G$143 -> 0.36018355
B86: 3 Advances received for the orders | C86: 0 | E86: 0 | G86: 0
B87: 4 Trade payables - suppliers | C87: 0 | E87: 0 | G87: 0
B88: 5 Bills of exchange payable | C88: 0 | E88: 0 | G88: 0
B89: 6 Amounts owed to affiliated entities | C89: 0 | E89: 0 | G89: 0
B90: 7 Amounts owed to associated entities and jointly controlled entities | C90: 0 | E90: 0 | G90: 0
B91: 8 Other debts, including fiscal debts and debts related to social securities | C91: 342841.79 | D91: =$C91/$C$143 -> 0.016250165 | E91: 403857.49 | F91: =$E91/$E$143 -> 0.021471221 | G91: 211459.79 | H91: =$G91/$G$143 -> 0.013735499
B92: TOTAL | C92: =SUM(C84:C91) -> 11184826 | D92: =$C92/$C$143 -> 0.53014331 | E92: =SUM(E84:E91) -> 9012984.1 | F92: =$E92/$E$143 -> 0.47917837 | G92: =SUM(G84:G91) -> 5756532.4 | H92: =$G92/$G$143 -> 0.37391905
B94: PROVISIONS | C94: 0 | E94: 0 | G94: 0
B95: 1 Provisions for employee benefits | C95: 0 | E95: 0 | G95: 0
B96: 2 Provisions for taxes | C96: 0 | E96: 0 | G96: 0
B97: 3 Other provisions | C97: 0 | E97: 0 | G97: 0
B98: TOTAL PROVISIONS | C98: 0 | E98: 0 | G98: 0
B99: INCOME IN ADVANCE | C99: 0 | E99: 0 | G99: 0
B100: 1 Investment subsidies | C100: 0 | E100: 0 | G100: 0
B101: Amounts to be resumed in a period of up to one year | C101: 0 | E101: 0 | G101: 0
B102: Amounts to be resumed in a period of more than one year | C102: 0 | E102: 0 | G102: 0
B103: 2 Deferred income | C103: 0 | E103: 0 | G103: 0
B104: Amounts to be resumed in a period of up to one year | C104: 0 | E104: 0 | G104: 0
B105: Amounts to be resumed in a period of more than one year | C105: 0 | E105: 0 | G105: 0
... B111: CAPITAL AND RESERVES | C111: 0 | E111: 0 | G111: 0
B112: 1 Subscribed and paid up share capital | C112: 2020.6102 | D112: =$C112/$C$143 -> 9.577377e-05 | E112: 2010.0503 | F112: =$E112/$E$143 -> 0.00010686501 | G112: 2010.4544 | H112: =$G112/$G$143 -> 0.00013059028
B113: 2 Subscribed and not paid share capital | C113: 0 | E113: 0 | G113: 0
B114: 3 Patrimony (autonomus companies) | C114: 0 | E114: 0 | G114: 0
B115: 4 Patrimony of national institutions for research and development | C115: 0 | E115: 0 | G115: 0
B116: 5 Other equity elements | C116: 0 | E116: 0 | G116: 0
...

Sheet Tabelle1
E2: EUR vs. RON | F2: EUR vs. RON
C3: BALANCE SHEET | E3: 45655 | F3: 45657
C4: as at December 31, 2024 | E4: 4.975 | F4: 4.974
C6: No. Description | D6: Row no. | E6: as at December 31, 2023 | F6: as at December 31, 2024
C7: NON-CURRENT ASSETS
C9: I. INTANGIBLE ASSETS
C10: 1 Set-up expenses (acc. 201 - 2801) | D10: 1 | E10: 0 | F10: 0
C11: 2 Development expenses (acc. 2023 - 2803 - 2903) | D11: 2 | E11: 0 | F11: 0
C12: 3 Concessions, patents, licenses, trademarks, similar rights and assets and other intangible assets (acc. 205 + 208 - 2805 - 2808 - 2905 - 2908) | D12: 3 | E12: 127288 | F12: 99398
C13: 4 Goodwill (acc. 2071 - 2807) | D13: 4 | E13: 0 | F13: 0
C14: 5 Intangible exploration assets and evaluation of mineral resources (206 - 2806 - 2906) | D14: 5 | E14: 0 | F14: 0
C15: 6 Advances (acc. 4094 - 4904) | D15: 6 | E15: 0 | F15: 0
C16: TOTAL (row 01 to 06) | D16: 7 | E16: 127288 | F16: 99398
E17: =E16/E4 -> 25585.528 | F17: =F16/F4 -> 19983.514
C18: Test | E18: =E17-'Balance Sheet 2022-2024 (2)'!E16 -> 0 | F18: =F17-'Balance Sheet 2022-2024 (2)'!G16 -> 0
C20: II. TANGIBLE ASSETS
C21: 1 Land and buildings (acc. 211 + 212 - 2811 - 2812 - 2911 - 2912) | D21: 8 | E21: 7228006 | F21: 6817701
C22: 2 Installations and machinery (acc. 213 + 223 - 2813 - 2913) | D22: 9 | E22: 29155422 | F22: 17677934
C23: 3 Other installations, machines and furniture (acc. 214 + 224 - 2814 - 2914) | D23: 10 | E23: 384377 | F23: 770795
C24: 4 Investment property (acc. 215 - 2815 - 2915) | D24: 11 | E24: 0 | F24: 0
C25: 5 Tangible assets in progress (acc. 231 - 2931) | D25: 12 | E25: 0 | F25: 0
C26: 6 Investment property in progress (acc. 235 - 2935) | D26: 13 | E26: 0 | F26: 0
C27: 7 Tangible assets for exploration and valuation of mineral resources (acc. 216 - 2816 - 2916) | D27: 14 | E27: 0 | F27: 0
C28: 8 Productive biological assets (acc. 217 + 227 - 2817 - 2917) | D28: 15 | E28: 0 | F28: 0
C29: 9 Advances (acc. 4093 - 4903) | D29: 16 | E29: 0 | F29: 497410
C30: TOTAL (row 08 to 16) | D30: 17 | E30: 36767805 | F30: 25763840
E31: =E30/E4 -> 7390513.6 | F31: =F30/F4 -> 5179702.5
C32: Test | E32: =E31-'Balance Sheet 2022-2024 (2)'!E27 -> 0 | F32: =F31-'Balance Sheet 2022-2024 (2)'!G27 -> 0
C34: III. FINANCIAL ASSETS
C35: 1 Investments in related parties (acc. 261 - 2961) | D35: 18 | E35: 0 | F35: 0
C36: 2 Loans granted to related parties (acc. 2671 + 2671 - 2964) | D36: 19 | E36: 0 | F36: 0
C37: 3 Equity investment (acc. 262 + 263 - 2962) | D37: 20 | E37: 0 | F37: 0
C38: 4 Loans granted to associated entities and jointly controlled entities (acc. 2673 + 2674 - 2965) | D38: 21 | E38: 0 | F38: 0
C39: 5 Other fixed assets (acc. 265 + 266 - 2963) | D39: 22 | E39: 0 | F39: 0
C40: 6 Other loans (acc. 2675* + 2676* + 2677 + 2678* + 2679* - 2966* - 2968*) | D40: 23 | E40: 51634 | F40: 50127
C41: TOTAL (row 18 to 23) | D41: 24 | E41: 51634 | F41: 50127
E42: =E41/E4 -> 10378.693 | F42: =F41/F4 -> 10077.805
C43: Test | E43: =E42-'Balance Sheet 2022-2024 (2)'!E35 -> 0 | F43: =F42-'Balance Sheet 2022-2024 (2)'!G35 -> 0
C45: TOTAL NON-CURRENT ASSETS (row 07+17+24) | D45: 25 | E45: 36946727 | F45: 25913365
E46: =E45/E4 -> 7426477.8 | F46: =F45/F4 -> 5209763.8
C47: Test | E47: =E46-'Balance Sheet 2022-2024 (2)'!E37 -> 0 | F47: =F46-'Balance Sheet 2022-2024 (2)'!G37 -> 0
C50: CURRENT ASSETS
C51: I. INVENTORIES
C52: 1 Raw materials and consumables (acc. 301 + 302 + 303 +/- 308 +321 + 322 + 323 + 328 + 351 + 358 + 381 +/- 388 - 391 - 392 - 3951 - 3958 - 398) | D52: 26 | E52: 662608 | F52: 702683
C53: 2 Production in progress (acc. 331 + 332 +341 +/- 348* - 393 - 3941 - 3952) | D53: 27 | E53: 0 | F53: 0
C54: 3 Finished goods and commodities (acc. 327 + 345 + 346 + 347 +/- 348* + 354 + 356 + 357 + 361 + 326 +/- 368 + 371 +/- 378 - 3945 - 3946 - 3947 - 3953 - 3954 - 3955 - 3956 - 3957 - 396 - 397 - din ct 4428) | D54: 28 | E54: 0 | F54: 0
C55: 4 Advances (acc. 4091 - 4901) | D55: 29 | E55: 0 | F55: 0
C56: TOTAL (row 26 to 29) | D56: 30 | E56: 662608 | F56: 702683
E57: =E56/E4 -> 133187.54 | F57: =F56/F4 -> 141271.21
C58: Test | E58: =E57-'Balance Sheet 2022-2024 (2)'!E45 -> 0 | F58: =F57/'Balance Sheet 2022-2024 (2)'!G45 -> 1
C60: II. RECEIVABLES
C61: 1 Trade receivables (acc. 2675* + 2676* + 2678* + 2679* - 2966* - 2968* + 4092 + 411 + 413 + 418 - 4902 - 491) | D61: 31 | E61: 28740852 | F61: 25126157
C62: 2 Receivables from affiliated entities (acc. 451** - 495*) | D62: 32 | E62: 19786246 | F62: 6860383
C63: 3 Receivables from associated entities and jointly controlled entities (acc. 453** - 495*) | D63: 33 | E63: 0 | F63: 0
C64: 4 Other receivables (ct 425 + 4282 + 431** + 436**+437** + 4382 + 441** + 4424 + din ct 4428** + 444** + 445 + 446 ** + 447** + 4482 + 4582 + 4662 + 461 + 473** - 496 + 5187) | D64: 34 | E64: 1165551 | F64: 1601891
C65: 5 Subscribed and not paid capital (acc. 456 - 495*) | D65: 35 | E65: 0 | F65: 0
C66: 6 Dividends receivables for interim distributions (acc. 463) | D66: 36 | E66: 0 | F66: 0
C67: TOTAL (row 31 to 36) | D67: 37 | E67: 49692651 | F67: 33588431
E68: =E67/E4 -> 9988472.6 | F68: =F67/F4 -> 6752800.8
C69: Test | E69: =E68-'Balance Sheet 2022-2024 (2)'!E53 -> 0 | F69: =F68-'Balance Sheet 2022-2024 (2)'!G53 -> 0
C72: III. SHORT TERM INVESTMENTS
C73: 1 Shares owned in affiliated entities (acc. 501 - 591) | D73: 38 | E73: 0 | F73: 0
C74: 2 Other short-term investments (acc. 505 + 506 + 507 + din ct 508 - 595 - 596 - 598 + 5113 + 5114) | D74: 39 | E74: 0 | F74: 0
C75: TOTAL (row 38 to 39) | D75: 40 | E75: 0 | F75: 0
C76: IV PETTY CASH AND BANK ACCOUNTS (acc. 508 + ct 5112 + 512 + 531 + 532 + 541 + 542) | D76: 41 | E76: 5409137 | F76: 15400127
E77: =E76/E4 -> 1087263.7 | F77: =F76/F4 -> 3096125.3
C78: Test | E78: =E77-'Balance Sheet 2022-2024 (2)'!E58 -> 0
C80: TOTAL CURRENT ASSETS (row 30+37+40+41) | D80: 42 | E80: 55764396 | F80: 49691241
E81: =E80/E4 -> 11208924 | F81: =F80/F4 -> 9990197.2
C82: Test | E82: =E81-'Balance Sheet 2022-2024 (2)'!E60 -> 0

Sheet Overview BS
B2: Original Version | L2: Original Translated Version | R2: Steinbeis Version in €
R3: in €
B4: Nr. crt. | C4: Nr. rd. | D4: Mapping | F4: FY23 | H4: sold la 31.09.2024 | J4: FY24 | L4: No. Description | M4: Row no. | N4: FY23 | O4: FY24 | P4: Variation - RON - | R4: No. Description | S4: FY22 | U4: FY23 | W4: FY24
B5: ACTIVE IMOBILIZATE | L5: NON-CURRENT ASSETS | R5: NON-CURRENT ASSETS
B6: I. IMOBILIZĂRI NECORPORALE | L6: I. INTANGIBLE ASSETS | R6: I. INTANGIBLE ASSETS
B7: 1 Cheltuieli de constituire (ct 201 - 2801) | C7: 1 | D7: INTANGIBLES | F7: 0 | H7: 0 | J7: 0 | L7: 1 Set-up expenses (acc. 201 - 2801) | M7: =C7 -> 1 | N7: 0 | O7: 0 | P7: =O7-N7 -> 0 | R7: 1 Set-up expenses | S7: 0 | U7: 0 | W7: 0
B8: 2 Cheltuieli de dezvoltare (ct 203 - 2803 - 2903) | C8: 2 | D8: INTANGIBLES | F8: 0 | H8: 0 | J8: 0 | L8: 2 Development expenses (acc. 2023 - 2803 - 2903) | M8: =C8 -> 2 | N8: =F8 -> 0 | O8: =J8 -> 0 | P8: =O8-N8 -> 0 | R8: 2 Development expenses | S8: 0 | U8: 0 | W8: 0
B9: 3 Concesiuni, brevete, licente, marci comerciale, drepturi si active similare si alte imobilizari necorporale (ct 205 + 208 - 2805 - 2808 - 2905 - 2908) | C9: 3 | D9: INTANGIBLES | F9: 127288 | H9: 0 | J9: 99398 | L9: 3 Concessions, patents, licenses, trademarks, similar rights and assets and other intangible assets (acc. 205 + 208 - 2805 - 2808 - 2905 - 2908) | M9: =C9 -> 3 | N9: =F9 -> 127288 | O9: =J9 -> 99398 | P9: =O9-N9 -> -27890 | R9: 3 Concessions, patents, licenses, trademarks, similar rights and assets and other intangible assets | S9: 4011.3154 | T9: 0.00041856634 | U9: 25585.528 | V9: 0.0034451766 | W9: 19983.514 | X9: 0.0038357813
B10: 4 Fond comercial (ct 2071 - 2807) | C10: 4 | D10: INTANGIBLES | F10: 0 | H10: 0 | J10: 0 | L10: 4 Goodwill (acc. 2071 - 2807) | M10: =C10 -> 4 | N10: =F10 -> 0 | O10: =J10 -> 0 | P10: =O10-N10 -> 0 | R10: 4 Goodwill | S10: 0 | U10: 0 | W10: 0
B11: 5 Active necorporale de explorare si evaluare a resurselor minerale (206 - 2806 - 2906) | C11: 5 | D11: INTANGIBLES | F11: 0 | H11: 0 | J11: 0 | L11: 5 Intangible exploration assets and evaluation of mineral resources (206 - 2806 - 2906) | M11: =C11 -> 5 | N11: =F11 -> 0 | O11: =J11 -> 0 | P11: =O11-N11 -> 0 | R11: 5 Intangible exploration assets and evaluation of mineral resources | S11: 0 | U11: 0 | W11: 0
B12: 6 Avansuri (ct 4094 - 4904) | C12: 6 | D12: INTANGIBLES | F12: 0 | H12: 0 | J12: 0 | L12: 6 Advances (acc. 4094 - 4904) | M12: =C12 -> 6 | N12: =F12 -> 0 | O12: =J12 -> 0 | P12: =O12-N12 -> 0 | R12: 6 Advances | S12: 0 | U12: 0 | W12: 0
B13: TOTAL (rd. 01 la 06) | C13: 7 | F13: 127288 | H13: 0 | J13: 99398 | L13: TOTAL (row 01 to 06) | M13: =C13 -> 7 | N13: =F13 -> 127288 | O13: =J13 -> 99398 | P13: =O13-N13 -> -27890 | R13: TOTAL | S13: 4011.3154 | T13: 0.00019013009 | U13: 25585.528 | V13: 0.0013602633 | W13: 19983.514 | X13: 0.0012980413
B14: II. IMOBILIZĂRI CORPORALE | L14: II. TANGIBLE ASSETS | R14: II. TANGIBLE ASSETS | S14: 0 | U14: 0 | W14: 0
B15: 1 Terenuri si constructii (ct 211 + 212 - 2811 - 2812 - 2911 - 2912) | C15: 8 | D15: PROPERTY | F15: 7228006 | H15: 0 | J15: 6817701 | L15: 1 Land and buildings (acc. 211 + 212 - 2811 - 2812 - 2911 - 2912) | M15: =C15 -> 8 | N15: =F15 -> 7228006 | O15: =J15 -> 6817701 | P15: =O15-N15 -> -410305 | R15: 1 Land and buildings | S15: 1523198.8 | T15: 0.072197246 | U15: 1452865.5 | V15: 0.077242091 | W15: 1370667.7 | X15: 0.08903255
B16: 2 Instalatii tehnice si masini (ct 213 + 223 - 2813 - 2913) | C16: 9 | D16: PROPERTY | F16: 29155422 | H16: 0 | J16: 17677934 | L16: 2 Installations and machinery (acc. 213 + 223 - 2813 - 2913) | M16: =C16 -> 9 | N16: =F16 -> 29155422 | O16: =J16 -> 17677934 | P16: =O16-N16 -> -11477488 | R16: 2 Installations and machinery | S16: 7850724.8 | T16: 0.37211209 | U16: 5860386.3 | V16: 0.31156944 | W16: 3554068 | X16: 0.23085664
B17: 3 Alte instalatii, utilaje si mobilier (ct 214 + 224 - 2814 - 2914) | C17: 10 | D17: PROPERTY | F17: 384377 | H17: 0 | J17: 770795 | L17: 3 Other installations, machines and furniture (acc. 214 + 224 - 2814 - 2914) | M17: =C17 -> 10 | N17: =F17 -> 384377 | O17: =J17 -> 770795 | P17: =O17-N17 -> 386418 | R17: 3 Other installations, machines and furniture | S17: 76867.448 | T17: 0.003643397 | U17: 77261.709 | V17: 0.0041076451 | W17: 154964.82 | X17: 0.010065834
B18: 4 Investitii imobiliare (ct 215 - 2815 - 2915) | C18: 11 | D18: PROPERTY | F18: 0 | H18: 0 | J18: 0 | L18: 4 Investment property (acc. 215 - 2815 - 2915) | M18: =C18 -> 11 | N18: =F18 -> 0 | O18: =J18 -> 0 | P18: =O18-N18 -> 0 | R18: 4 Investment property | S18: 0 | U18: 0 | W18: 0
B19: 5 Imobilizari corporale in curs de executie (ct 231 - 2931) | C19: 12 | D19: PROPERTY | F19: 0 | H19: 0 | J19: 0 | L19: 5 Tangible assets in progress (acc. 231 - 2931) | M19: =C19 -> 12 | N19: =F19 -> 0 | O19: =J19 -> 0 | P19: =O19-N19 -> 0 | R19: 5 Tangible assets in progress | S19: 4992.5237 | T19: 0.00023663783 | U19: 0 | W19: 0
B20: 6 Investitii imobiliare in curs de executie (ct 235 - 2935) | C20: 13 | D20: PROPERTY | F20: 0 | H20: 0 | J20: 0 | L20: 6 Investment property in progress (acc. 235 - 2935) | M20: =C20 -> 13 | N20: =F20 -> 0 | O20: =J20 -> 0 | P20: =O20-N20 -> 0 | R20: 6 Investment property in progress | S20: 0 | U20: 0 | W20: 0
B21: 7 Active corporale de explorare si evaluare a resurselor minerale (ct 216 - 2816 - 2916) | C21: 14 | D21: PROPERTY | F21: 0 | H21: 0 | J21: 0 | L21: 7 Tangible assets for exploration and valuation of mineral resources (acc. 216 - 2816 - 2916) | M21: =C21 -> 14 | N21: =F21 -> 0 | O21: =J21 -> 0 | P21: =O21-N21 -> 0 | R21: 7 Tangible assets for exploration and valuation of mineral resources | S21: 0 | U21: 0 | W21: 0
B22: 8 Active biologice productive (ct 217 + 227 - 2817 - 2917) | C22: 15 | D22: PROPERTY | F22: 0 | H22: 0 | J22: 0 | L22: 8 Productive biological assets (acc. 217 + 227 - 2817 - 2917) | M22: =C22 -> 15 | N22: =F22 -> 0 | O22: =J22 -> 0 | P22: =O22-N22 -> 0 | R22: 8 Productive biological assets | S22: 0 | U22: 0 | W22: 0
B23: 9 Avansuri (ct 4093 - 4903) | C23: 16 | D23: PROPERTY | F23: 0 | H23: 0 | J23: 497410 | L23: 9 Advances (acc. 4093 - 4903) | M23: =C23 -> 16 | N23: =F23 -> 0 | O23: =J23 -> 497410 | P23: =O23-N23 -> 497410 | R23: 9 Advances | S23: 120859.57 | T23: 0.0057285547 | U23: 0 | W23: 100002.01 | X23: 0.0064956913
B24: TOTAL (rd. 08 la 16) | C24: 17 | F24: 36767805 | H24: 0 | J24: 25763840 | L24: TOTAL (row 08 to 16) | M24: =C24 -> 17 | N24: =F24 -> 36767805 | O24: =J24 -> 25763840 | P24: =O24-N24 -> -11003965 | R24: TOTAL | S24: 9576643.2 | T24: 0.45391793 | U24: 7390513.6 | V24: 0.39291917 | W24: 5179702.5 | X24: 0.33645071
B25: III. IMOBILIZĂRI FINANCIARE | L25: III. FINANCIAL ASSETS | R25: III. FINANCIAL ASSETS | S25: 0 | U25: 0 | W25: 0
B26: 1 Actiuni detinute la filiale (ct 261 - 2961) | C26: 18 | D26: FINANCIAL ASSETS | F26: 0 | H26: 0 | J26: 0 | L26: 1 Investments in related parties (acc. 261 - 2961) | M26: =C26 -> 18 | N26: =F26 -> 0 | O26: =J26 -> 0 | P26: =O26-N26 -> 0 | R26: 1 Investments in related parties | S26: 0 | U26: 0 | W26: 0
B27: 2 Imprumuturi acordate entitatilor din grup (ct 2671 + 2672 - 2964) | C27: 19 | D27: FINANCIAL ASSETS | F27: 0 | H27: 0 | J27: 0 | L27: 2 Loans granted to related parties (acc. 2671 + 2671 - 2964) | M27: =C27 -> 19 | N27: =F27 -> 0 | O27: =J27 -> 0 | P27: =O27-N27 -> 0 | R27: 2 Loans granted to related parties | S27: 0 | U27: 0 | W27: 0
B28: 3 Actiunile detinute la entitatile asociate si la entitatile controlate in comun (ct 262 + 263 - 2962) | C28: 20 | D28: FINANCIAL ASSETS | F28: 0 | H28: 0 | J28: 0 | L28: 3 Equity investment (acc. 262 + 263 - 2962) | M28: =C28 -> 20 | N28: =F28 -> 0 | O28: =J28 -> 0 | P28: =O28-N28 -> 0 | R28: 3 Equity investment | S28: 0 | U28: 0 | W28: 0
B29: 4 Imprumuturi acordate entitatilor asociate si entitatilor controlate in comun (ct 2673 + 2674 - 2965) | C29: 21 | D29: FINANCIAL ASSETS | F29: 0 | H29: 0 | J29: 0 | L29: 4 Loans granted to associated entities and jointly controlled entities (acc. 2673 + 2674 - 2965) | M29: =C29 -> 21 | N29: =F29 -> 0 | O29: =J29 -> 0 | P29: =O29-N29 -> 0 | R29: 4 Loans granted to associated entities and jointly controlled entities | S29: 0 | U29: 0 | W29: 0
B30: 5 Alte titluri imobilizate (ct 265 - 2963) | C30: 22 | D30: FINANCIAL ASSETS | F30: 0 | H30: 0 | J30: 0 | L30: 5 Other fixed assets (acc. 265 + 266 - 2963) | M30: =C30 -> 22 | N30: =F30 -> 0 | O30: =J30 -> 0 | P30: =O30-N30 -> 0 | R30: 5 Other fixed assets | S30: 0 | U30: 0 | W30: 0
B31: 6 Alte imprumuturi (ct 2675* + 2676* + 2677 + 2678* + 2679* - 2966* - 2968*) | C31: 23 | D31: FINANCIAL ASSETS | F31: 51634 | H31: 0 | J31: 50127 | L31: 6 Other loans (acc. 2675* + 2676* + 2677 + 2678* + 2679* - 2966* - 2968*) | M31: =C31 -> 23 | N31: =F31 -> 51634 | O31: =J31 -> 50127 | P31: =O31-N31 -> -1507 | R31: 6 Other loans | S31: 2809.4565 | T31: 0.00013316385 | U31: 10378.693 | V31: 0.00055178678 | W31: 10077.805 | X31: 0.00065460991
B32: TOTAL (rd. 18 la 23) | C32: 24 | F32: 51634 | H32: 0 | J32: 50127 | L32: TOTAL (row 18 to 23) | M32: =C32 -> 24 | N32: =F32 -> 51634 | O32: =J32 -> 50127 | P32: =O32-N32 -> -1507 | R32: TOTAL | S32: 2809.4565 | T32: 0.00013316385 | U32: 10378.693 | V32: 0.00055178678 | W32: 10077.805 | X32: 0.00065460991
B33: ACTIVE IMOBILIZATE - TOTAL (rd. 07+17+24) | C33: 25 | F33: 36946727 | H33: 0 | J33: 25913365 | L33: TOTAL NON-CURRENT ASSETS (row 07+17+24) | M33: =C33 -> 25 | N33: =F33 -> 36946727 | O33: =J33 -> 25913365 | P33: =O33-N33 -> -11033362 | R33: TOTAL NON-CURRENT ASSETS | S33: 9583463.9 | T33: 0.45424122 | U33: 7426477.8 | V33: 0.39483122 | W33: 5209763.8 | X33: 0.33840337
B34: ACTIVE CIRCULANTE | L34: CURRENT ASSETS | R34: CURRENT ASSETS | S34: 0 | U34: 0 | W34: 0
B35: I. STOCURI | L35: I. INVENTORIES | R35: I. INVENTORIES | S35: 0 | U35: 0 | W35: 0
B36: 1 Materii prime si materiale consumabile (ct 301 + 302 + 303 +/- 308 +321 + 322 + 323 + 328 + 351 + 358 + 381 +/- 388 - 391 - 392 - 3951 - 3958 - 398) | C36: 26 | D36: INVENTORY | F36: 662608 | H36: 0 | J36: 702683 | L36: 1 Raw materials and consumables (acc. 301 + 302 + 303 +/- 308 +321 + 322 + 323 + 328 + 351 + 358 + 381 +/- 388 - 391 - 392 - 3951 - 3958 - 398) | M36: =C36 -> 26 | N36: =F36 -> 662608 | O36: =J36 -> 702683 | P36: =O36-N36 -> 40075 | R36: 1 Raw materials and consumables | S36: 144370.78 | T36: 0.0068429496 | U36: 133187.54 | V36: 0.0070809609 | W36: 141271.21 | X36: 0.0091763572
B37: 2 Productia in curs de executie (ct 331 + 332 + 341 +/- 348* - 393 - 3941 - 3952) | C37: 27 | D37: INVENTORY | F37: 0 | H37: 0 | J37: 0 | L37: 2 Production in progress (acc. 331 + 332 +341 +/- 348* - 393 - 3941 - 3952) | M37: =C37 -> 27 | N37: =F37 -> 0 | O37: =J37 -> 0 | P37: =O37-N37 -> 0 | R37: 2 Production in progress | S37: 0 | U37: 0 | W37: 0
B38: 3 Produse finite si marfuri (ct 327 + 345 + 346 + 347 +/- 348* + 354 + 356 + 357 + 361 + 326 +/- 368 + 371 +/- 378 - 3945 - 3946 - 3947 - 3953 - 3954 - 3955 - 3956 - 3957 - 396 - 397 - din ct 4428) | C38: 28 | D38: INVENTORY | F38: 0 | H38: 0 | J38: 0 | L38: 3 Finished goods and commodities (acc. 327 + 345 + 346 + 347 +/- 348* + 354 + 356 + 357 + 361 + 326 +/- 368 + 371 +/- 378 - 3945 - 3946 - 3947 - 3953 - 3954 - 3955 - 3956 - 3957 - 396 - 397 - din ct 4428) | M38: =C38 -> 28 | N38: =F38 -> 0 | O38: =J38 -> 0 | P38: =O38-N38 -> 0 | R38: 3 Finished goods and commodities | S38: 0 | U38: 0 | W38: 0
B39: 4 Avansuri (ct 4091 - 4901) | C39: 29 | D39: INVENTORY | F39: 0 | H39: 0 | J39: 0 | L39: 4 Advances (acc. 4091 - 4901) | M39: =C39 -> 29 | N39: =F39 -> 0 | O39: =J39 -> 0 | P39: =O39-N39 -> 0 | R39: 4 Advances | S39: 0 | U39: 0 | W39: 0
B40: TOTAL (rd. 26 la 29) | C40: 30 | F40: 662608 | H40: 0 | J40: 702683 | L40: TOTAL (row 26 to 29) | M40: =C40 -> 30 | N40: =F40 -> 662608 | O40: =J40 -> 702683 | P40: =O40-N40 -> 40075 | R40: TOTAL | S40: 144370.78 | T40: 0.0068429496 | U40: 133187.54 | V40: 0.0070809609 | W40: 141271.21 | X40: 0.0091763572
B41: II. CREANȚE | L41: II. RECEIVABLES | R41: II. RECEIVABLES | S41: 0 | U41: 0 | W41: 0
B42: 1 Creante comerciale (ct 2675* + 2676* + 2678* + 2679* - 2966* - 2968* + 4092 + 411 + 413 + 418 - 4902 - 491) | C42: 31 | D42: RECEIVABLES | F42: 28740852 | H42: 0 | J42: 25126157 | L42: 1 Trade receivables (acc. 2675* + 2676* + 2678* + 2679* - 2966* - 2968* + 4092 + 411 + 413 + 418 - 4902 - 491) | M42: =C42 -> 31 | N42: =F42 -> 28740852 | O42: =J42 -> 25126157 | P42: =O42-N42 -> -3614695 | R42: 1 Trade receivables | S42: 6410442.7 | T42: 0.30384497 | U42: 5777055.7 | V42: 0.30713913 | W42: 5051499.2 | X42: 0.32812319
B43: 2 Sume de incasat de la entitatile afiliate (ct 451** - 495*) | C43: 32 | D43: RECEIVABLES | F43: 19786246 | H43: 0 | J43: 6860383 | L43: 2 Receivables from affiliated entities (acc. 451** - 495*) | M43: =C43 -> 32 | N43: =F43 -> 19786246 | O43: =J43 -> 6860383 | P43: =O43-N43 -> -12925863 | R43: 2 Receivables from affiliated entities | S43: 508999.8 | T43: 0.024125795 | U43: 3977135.3 | V43: 0.21144575 | W43: 1379248.7 | X43: 0.089589936
B44: 3 Sume de incasat de la entitatile asociate si entitatile controlate in comun (ct 453** - 495*) | C44: 33 | D44: RECEIVABLES | F44: 0 | H44: 0 | J44: 0 | L44: 3 Receivables from associated entities and jointly controlled entities (acc. 453** - 495*) | M44: =C44 -> 33 | N44: =F44 -> 0 | O44: =J44 -> 0 | P44: =O44-N44 -> 0 | R44: 3 Receivables from associated entities and jointly controlled entities | S44: 0 | U44: 0 | W44: 0
B45: 4 Alte creante (ct 425 + 4282 + 431** + 436**+437** + 4382 + 441** + 4424 + din ct 4428** + 444** + 445 + 446 ** + 447** + 4482 + 4582 + 4662 + 461 + 473** - 496 + 5187) | C45: 34 | D45: RECEIVABLES | F45: 1165551 | H45: 0 | J45: 1601891 | L45: 4 Other receivables (ct 425 + 4282 + 431** + 436**+437** + 4382 + 441** + 4424 + din ct 4428** + 444** + 445 + 446 ** + 447** + 4482 + 4582 + 4662 + 461 + 473** - 496 + 5187) | M45: =C45 -> 34 | N45: =F45 -> 1165551 | O45: =J45 -> 1601891 | P45: =O45-N45 -> 436340 | R45: 4 Other receivables | S45: 982636.69 | T45: 0.046575445 | U45: 234281.61 | V45: 0.012455662 | W45: 322052.87 | X45: 0.02091914
B46: 5 Capital subscris si nevarsat (ct 456 - 495*) | C46: 35 | D46: RECEIVABLES | F46: 0 | H46: 0 | J46: 0 | L46: 5 Subscribed and not paid capital (acc. 456 - 495*) | M46: =C46 -> 35 | N46: =F46 -> 0 | O46: =J46 -> 0 | P46: =O46-N46 -> 0 | R46: 5 Subscribed and not paid capital | S46: 0 | U46: 0 | W46: 0
B47: 6 Creanțe reprezentând dividende repartizate în cursul exercițiului financiar (ct. 463) | C47: 36 | F47: 0 | H47: 0 | J47: 0 | L47: 6 Dividends receivables for interim distributions (acc. 463) | M47: =C47 -> 36 | N47: =F47 -> 0 | O47: =J47 -> 0 | P47: =O47-N47 -> 0 | R47: 6 Dividends receivables for interim distributions | S47: 0 | U47: 0 | W47: 0
B48: TOTAL (rd 31. la 36) | C48: 37 | F48: 49692651 | H48: 0 | J48: 33588431 | L48: TOTAL (row 31 to 36) | M48: =C48 -> 37 | N48: =F48 -> 49692651 | O48: =J48 -> 33588431 | P48: =O48-N48 -> -16104220 | R48: TOTAL | S48: 7902079.2 | T48: 0.37454621 | U48: 9988472.6 | V48: 0.53104055 | W48: 6752800.8 | X48: 0.43863227
B49: III. INVESTIȚII PE TERMEN SCURT | L49: III. SHORT TERM INVESTMENTS | R49: III. SHORT TERM INVESTMENTS | S49: 0 | U49: 0 | W49: 0
B50: 1 Actiuni detinute la entitatile afiliate (ct 501 - 591) | C50: 38 | D50: SHORT-TERM INVESTMENTS | F50: 0 | H50: 0 | J50: 0 | L50: 1 Shares owned in affiliated entities (acc. 501 - 591) | M50: =C50 -> 38 | N50: =F50 -> 0 | O50: =J50 -> 0 | P50: =O50-N50 -> 0 | R50: 1 Shares owned in affiliated entities | S50: 0 | U50: 0 | W50: 0
B51: 2 Alte investitii pe termen scurt (ct 505 + 506 + 507 + din ct 508 - 595 - 596 - 598 + 5113 + 5114) | C51: 39 | D51: SHORT-TERM INVESTMENTS | F51: 0 | H51: 0 | J51: 0 | L51: 2 Other short-term investments (acc. 505 + 506 + 507 + din ct 508 - 595 - 596 - 598 + 5113 + 5114) | M51: =C51 -> 39 | N51: =F51 -> 0 | O51: =J51 -> 0 | P51: =O51-N51 -> 0 | R51: 2 Other short-term investments | S51: 0 | U51: 0 | W51: 0
B52: TOTAL (rd. 38 + 39) | C52: 40 | F52: 0 | H52: 0 | J52: 0 | L52: TOTAL (row 38 to 39) | M52: =C52 -> 40 | N52: =F52 -> 0 | O52: =J52 -> 0 | P52: =O52-N52 -> 0 | R52: TOTAL | S52: 0 | U52: 0 | W52: 0
B53: IV CASA SI CONTURI LA BANCI (din ct 508 + ct 5112 + 512 + 531 + 532 + 541 + 542) | C53: 41 | D53: CASH | F53: 5409137 | H53: 0 | J53: 15400127 | L53: IV PETTY CASH AND BANK ACCOUNTS (acc. 508 + ct 5112 + 512 + 531 + 532 + 541 + 542) | M53: =C53 -> 41 | N53: =F53 -> 5409137 | O53: =N53*1.17 -> 6328690.3 | P53: =O53-N53 -> 919553.29 | R53: IV PETTY CASH AND BANK ACCOUNTS | S53: 3309318 | T53: 0.15685651 | U53: 1087263.7 | V53: 0.057804746 | W53: 1272354.3 | X53: 0.082646545
B54: ACTIVE CIRCULANTE - TOTAL (rd. 30+37+40+41) | C54: 42 | F54: 55764396 | H54: 0 | J54: 49691241 | L54: TOTAL CURRENT ASSETS (row 30+37+40+41) | M54: =C54 -> 42 | N54: =F54 -> 55764396 | O54: =J54 -> 49691241 | P54: =O54-N54 -> -6073155 | R54: TOTAL CURRENT ASSETS | S54: 11355768 | T54: 0.53824567 | U54: 11208924 | V54: 0.59592626 | W54: 9990197.2 | X54: 0.64891932
B55: CHELTUIELI IN AVANS (ct 471 + 474) (rd 44 + 45) | C55: 43 | D55: PREPAYMENTS | F55: 864878 | H55: 0 | J55: 970770 | L55: PREPAYMENTS (acc 471 + 474) (row 44 + 45) | M55: =C55 -> 43 | N55: =F55 -> 864878 | O55: =J55 -> 970770 | P55: =O55-N55 -> 105892 | R55: PREPAYMENTS | S55: 158509.6 | T55: 0.0075131074 | U55: 173844.82 | V55: 0.0092425194 | W55: 195168.88 | X55: 0.012677313
B56: Sume de reluat intr-o perioada de pana la un an (din ct 471* + 474) | C56: 44 | F56: 864878 | H56: 0 | J56: 970770 | L56: Amounts to be resumed in a period of up to one year (acc. 471* + 474) | M56: =C56 -> 44 | N56: =F56 -> 864878 | O56: =J56 -> 970770 | P56: =O56-N56 -> 105892 | R56: Amounts to be resumed in a period of up to one year | S56: 158509.6 | T56: 0.0075131074 | U56: 173844.82 | V56: 0.0092425194 | W56: 0 | X56: 0
B57: Sume de reluat intr-o perioada mai mare de un an (din ct 471* + 474) | C57: 45 | F57: 0 | H57: 0 | J57: 0 | L57: Amounts to be resumed in a period of more than one year (acc. 471* + 474) | M57: =C57 -> 45 | N57: =F57 -> 0 | O57: =J57 -> 0 | P57: =O57-N57 -> 0 | R57: Amounts to be resumed in a period of more than one year | S57: 0 | U57: 0 | W57: 0
R58: Total Assets | S58: 21097742 | T58: 1 | U58: 18809246 | V58: 1 | W58: 15395130 | X58: 1
R59: Growth in % | U59: -0.1084711 | W59: -0.18151267
B60: DATORII: SUMELE CARE TREBUIE PLĂTITE ÎNTR-O PERIOADĂ DE PÂNĂ LA UN AN | L60: Payables: Amounts to be paid in a period of up to one year | R60: Payables: Amounts to be paid in a period of up to one year | S60: 0 | U60: 0 | W60: 0
B61: 1 Imprumuturi din emisiuni de obligatiuni, prezentandu-se separat imprumuturile din emisiunea de obligatiuni convertibile (ct 161 +1681 - 169) | C61: 46 | D61: PAYABLES < 1Yr | F61: 0 | H61: 0 | J61: 0 | L61: 1 Loans from the issue of bonds; the issue of convertible bonds shall be disclosed separately (acc. 161 +1681 - 169) | M61: =C61 -> 46 | N61: =F61 -> 0 | O61: =J61 -> 0 | P61: =O61-N61 -> 0 | R61: 1 Loans from the issue of bonds; the issue of convertible bonds shall be disclosed separately | S61: 0 | U61: 0 | W61: 0
B62: 2 Sume datorate institutiilor de credit (ct 1621 + 1622 + 1624 + 1625 + 1627 + 1682 + 5191 + 5192 + 5198) | C62: 47 | D62: PAYABLES < 1Yr | F62: 15193916 | H62: 0 | J62: 15239101 | L62: 2 Amounts owed to credit institutions (acc. 1621 + 1622 + 1624 + 1625 + 1627 + 1682 + 5191 + 5192 + 5198) | M62: =C62 -> 47 | N62: =F62 -> 15193916 | O62: =J62 -> 15239101 | P62: =O62-N62 -> 45185 | R62: 2 Amounts owed to credit institutions | S62: 3183827.8 | T62: 0.15090847 | U62: 3054053.5 | V62: 0.16236979 | W62: 3063751.7 | X62: 0.19900785
B63: 3 Avansuri incasate in contul comenzilor (ct 419) | C63: 48 | D63: PAYABLES < 1Yr | F63: 61207 | H63: 0 | J63: 48733 | L63: 3 Advances received for the orders (acc. 419) | M63: =C63 -> 48 | N63: =F63 -> 61207 | O63: =J63 -> 48733 | P63: =O63-N63 -> -12474 | R63: 3 Advances received for the orders | S63: 11448.98 | T63: 0.00054266376 | U63: 12302.915 | V63: 0.00065408864 | W63: 9797.5472 | X63: 0.00063640562
B64: 4 Datorii comerciale - furnizori (ct 401 + 404 + 408) | C64: 49 | D64: PAYABLES < 1Yr | F64: 16360141 | H64: 0 | J64: 13949677 | L64: 4 Trade payables - suppliers (acc. 401 + 404 + 408) | M64: =C64 -> 49 | N64: =F64 -> 16360141 | O64: =J64 -> 13949677 | P64: =O64-N64 -> -2410464 | R64: 4 Trade payables - suppliers | S64: 3341737.7 | T64: 0.15839315 | U64: 3288470.6 | V64: 0.17483266 | W64: 2804518.9 | X64: 0.18216923
B65: 5 Efecte de comert de platit (ct 403 + 405) | C65: 50 | D65: PAYABLES < 1Yr | F65: 0 | H65: 0 | J65: 0 | L65: 5 Bills of exchange payable (acc. 403 + 405) | M65: =C65 -> 50 | N65: =F65 -> 0 | O65: =J65 -> 0 | P65: =O65-N65 -> 0 | R65: 5 Bills of exchange payable | S65: 0 | T65: 0 | U65: 0 | V65: 0 | W65: 0
B66: 6 Sume datorate entitatilor din grup (ct. 1661 + 1685 + 2691 + 451***) | C66: 51 | D66: PAYABLES < 1Yr | F66: 0 | H66: 0 | J66: 0 | L66: 6 Amounts owed to affiliated entities (acc. 1661 + 1685 + 2691 + 451***) | M66: =C66 -> 51 | N66: =F66 -> 0 | O66: =J66 -> 0 | P66: =O66-N66 -> 0 | R66: 6 Amounts owed to affiliated entities | S66: 0 | T66: 0 | U66: 0 | V66: 0 | W66: 0
B67: 7 Sume datorate entitatilor asociate si entitatlor controlate in comun (ct. 1663 + 1686 + 2692 + 2693 + 453***) | C67: 52 | D67: PAYABLES < 1Yr | F67: 0 | H67: 0 | J67: 0 | L67: 7 Amounts owed to associated entities and jointly controlled entities (acc. 1663 + 1686 + 2692 + 2693 + 453***) | M67: =C67 -> 52 | N67: =F67 -> 0 | O67: =J67 -> 0 | P67: =O67-N67 -> 0 | R67: 7 Amounts owed to associated entities and jointly controlled entities | S67: 899709.03 | T67: 0.042644803 | U67: 0 | V67: 0 | W67: 0
B68: 8 Alte datorii, inclusiv datoriile fiscale si datoriile privind asigurarile sociale pentru asigurarile sociale (ct. 1623 + 1626 + 167 + 1687 + 2695 + 421 + 423 + 424 + 426 + 427 + 4281 + 431*** + 436*** + 437*** + 4381 + 441*** + 4423 + 4428*** + 444*** + 446*** + 447*** + 4481 + 455 + 456*** + 457 + 4581 + 462 + 4661 + 467 + 473*** + 509 + 5186 + 5193 + 5194 + 5195 + 5196 + 5197) | C68: 53 | D68: PAYABLES < 1Yr | F68: 4430907 | H68: 0 | J68: 4225465 | L68: 8 Other debts, including fiscal debts and debts related to social securities (acc. 1623 + 1626 + 167 + 1687 + 2695 + 421 + 423 + 424 + 426 + 427 + 4281 + 431*** + 436*** + 437*** + 4381 + 441*** + 4423 + 4428*** + 444*** + 446*** + 447*** + 4481 + 455 + 456*** + 457 + 4581 + 462 + 4661 + 467 + 473*** + 509 + 5186 + 5193 + 5194 + 5195 + 5196 + 5197) | M68: =C68 -> 53 | N68: =F68 -> 4430907 | O68: =J68 -> 4225465 | P68: =O68-N68 -> -205442 | R68: 8 Other debts, including fiscal debts and debts related to social securities | S68: 868891.09 | T68: 0.041184081 | U68: 890634.77 | V68: 0.047350901 | W68: 849510.45 | X68: 0.055180467
B69: TOTAL (rd. 46 la 53) | C69: 54 | F69: 36046171 | H69: 0 | J69: 33462976 | L69: TOTAL (row 46 to 53) | M69: =C69 -> 54 | N69: =F69 -> 36046171 | O69: =J69 -> 33462976 | P69: =O69-N69 -> -2583195 | R69: TOTAL | S69: 8305614.7 | T69: 0.39367317 | U69: 7245461.7 | V69: 0.38520744 | W69: 6727578.6 | X69: 0.43699395
B70: ACTIVE CIRCULANTE NETE/DATORII CURENTE NETE) (rd. 42 + 44 - 54 - 71 - 74 - 77) | C70: 55 | F70: 20583103 | H70: 0 | J70: 17199035 | L70: E NET CURRENT ASSETS/NET CURRENT LIABILITIES (row 42 + 44 - 54 - 71 - 74 - 77) | M70: =C70 -> 55 | N70: =F70 -> 20583103 | O70: =J70 -> 17199035 | P70: =O70-N70 -> -3384068 | R70: E NET CURRENT ASSETS/NET CURRENT LIABILITIES | S70: 3208663 | T70: 0.15208561 | U70: 4137306.9 | V70: 0.21996133 | W70: 3457787.5 | X70: 0.22460268
B71: TOTAL ACTIVE MINUS DATORII CURENTE (rd. 25 + 45 + 55) | C71: 56 | F71: 57529830 | H71: 0 | J71: 43112400 | L71: F TOTAL ASSETS MINUS CURRENT LIABILITIES (row 25 + 45 + 55) | M71: =C71 -> 56 | N71: =F71 -> 57529830 | O71: =J71 -> 43112400 | P71: =O71-N71 -> -14417430 | R71: F TOTAL ASSETS MINUS CURRENT LIABILITIES | S71: 12792127 | T71: 0.60632684 | U71: 11563785 | V71: 0.61479255 | W71: 8667551.3 | X71: 0.56300605
B72: DATORII: SUMELE CARE TREBUIE PLĂTITE ÎNTR-O PERIOADĂ MAI MARE DE UN AN | L72: Payables: Amounts to be paid in a period of more than one year | R72: Payables: Amounts to be paid in a period of more than one year | S72: 0 | U72: 0 | W72: 0
B73: 1 Imprumuturi din emisiuni de obligatiuni, prezentandu-se separat imprumuturile din emisiunea de obligatiuni convertibile (ct 161 + 1681 - 169) | C73: 57 | D73: PAYABLES > 1Yr | F73: 0 | H73: 0 | J73: 0 | L73: 1 Loans from the issue of bonds; the issue of convertible bonds shall be disclosed separately (acc. 161 + 1681 - 169) | M73: =C73 -> 57 | N73: =F73 -> 0 | O73: =J73 -> 0 | P73: =O73-N73 -> 0 | R73: 1 Loans from the issue of bonds; the issue of convertible bonds shall be disclosed separately | S73: 0 | U73: 0 | W73: 0
B74: 2 Sume datorate institutiilor de credit (ct 1621 + 1622 + 1624 + 1625 + 1627 + 1682 + 5191 + 5192 + 5198) | C74: 58 | D74: PAYABLES > 1Yr | F74: 42830405 | H74: 0 | J74: 27581191 | L74: 2 Amounts owed to credit institutions (acc. 1621 + 1622 + 1624 + 1625 + 1627 + 1682 + 5191 + 5192 + 5198) | M74: =C74 -> 58 | N74: =F74 -> 42830405 | O74: =J74 -> 27581191 | P74: =O74-N74 -> -15249214 | R74: 2 Amounts owed to credit institutions | S74: 10841985 | T74: 0.51389314 | U74: 8609126.6 | V74: 0.45770715 | W74: 5545072.6 | X74: 0.36018355
B75: 3 Avansuri incasate in contul comenzilor (ct 419) | C75: 59 | D75: PAYABLES > 1Yr | F75: 0 | H75: 0 | J75: 0 | L75: 3 Advances received for the orders (acc. 419) | M75: =C75 -> 59 | N75: =F75 -> 0 | O75: =J75 -> 0 | P75: =O75-N75 -> 0 | R75: 3 Advances received for the orders | S75: 0 | U75: 0 | W75: 0
B76: 4 Datorii comerciale - furnizori (ct 401 + 404 + 408) | C76: 60 | D76: PAYABLES > 1Yr | F76: 0 | H76: 0 | J76: 0 | L76: 4 Trade payables - suppliers (acc. 401 + 404 + 408) | M76: =C76 -> 60 | N76: =F76 -> 0 | O76: =J76 -> 0 | P76: =O76-N76 -> 0 | R76: 4 Trade payables - suppliers | S76: 0 | U76: 0 | W76: 0
B77: 5 Efecte de comert de platit (ct 403 + 405) | C77: 61 | D77: PAYABLES > 1Yr | F77: 0 | H77: 0 | J77: 0 | L77: 5 Bills of exchange payable (acc. 403 + 405) | M77: =C77 -> 61 | N77: =F77 -> 0 | O77: =J77 -> 0 | P77: =O77-N77 -> 0 | R77: 5 Bills of exchange payable | S77: 0 | U77: 0 | W77: 0
B78: 6 Sume datorate entitatilor din grup (ct 1661 + 1685 + 2691 + 451***) | C78: 62 | D78: PAYABLES > 1Yr | F78: 0 | H78: 0 | J78: 0 | L78: 6 Amounts owed to affiliated entities (acc. 1661 + 1685 + 2691 + 451***) | M78: =C78 -> 62 | N78: =F78 -> 0 | O78: =J78 -> 0 | P78: =O78-N78 -> 0 | R78: 6 Amounts owed to affiliated entities | S78: 0 | U78: 0 | W78: 0
B79: 7 Sume datorate entitatilor asociate si entitatilor controlate in comun (ct 1663 + 1686 + 2692 + 2693 + 453***) | C79: 63 | D79: PAYABLES > 1Yr | F79: 0 | H79: 0 | J79: 0 | L79: 7 Amounts owed to associated entities and jointly controlled entities (acc. 1663 + 1686 + 2692 + 2693 + 453***) | M79: =C79 -> 63 | N79: =F79 -> 0 | O79: =J79 -> 0 | P79: =O79-N79 -> 0 | R79: 7 Amounts owed to associated entities and jointly controlled entities | S79: 0 | U79: 0 | W79: 0
B80: 8 Alte datorii, inclusiv datoriile fiscale si datoriile privind asigurarile sociale pentru asigurarile sociale (ct 1623 + 1626 + 167 + 1687 + 2695 + 421 + 423 + 424 + 426 + 427 + 4281 + 431*** + 436***+437*** + 4381 + 441*** + 4423 + 4428*** + 444*** + 446*** + 447*** + 4481 + 455 + 456*** + 4581 + 462 + 4661 + 467 + 473*** + 509 + 5186 + 5193 + 5194 + 5195 + 5196 + 5197) | C80: 64 | D80: PAYABLES > 1Yr | F80: 2009191 | H80: 0 | J80: 1051801 | L80: 8 Other debts, including fiscal debts and debts related to social securities (acc. 1623 + 1626 + 167 + 1687 + 2695 + 421 + 423 + 424 + 426 + 427 + 4281 + 431*** + 436***+437*** + 4381 + 441*** + 4423 + 4428*** + 444*** + 446*** + 447*** + 4481 + 455 + 456*** + 4581 + 462 + 4661 + 473*** + 509 + 5186 + 5193 + 5194 + 5195 + 5196 + 5197) | M80: =C80 -> 64 | N80: =F80 -> 2009191 | O80: =J80 -> 1051801 | P80: =O80-N80 -> -957390 | R80: 8 Other debts, including fiscal debts and debts related to social securities | S80: 342841.79 | T80: 0.016250165 | U80: 403857.49 | V80: 0.021471221 | W80: 211459.79 | X80: 0.013735499
B81: TOTAL (rd. 57 la 64) | C81: 65 | F81: 44839596 | H81: 0 | J81: 28632992 | L81: TOTAL (row 57 to 64) | M81: =C81 -> 65 | N81: =F81 -> 44839596 | O81: =J81 -> 28632992 | P81: =O81-N81 -> -16206604 | R81: TOTAL | S81: 11184826 | T81: 0.53014331 | U81: 9012984.1 | V81: 0.47917837 | W81: 5756532.4 | X81: 0.37391905
B82: PROVIZIOANE | L82: PROVISIONS | R82: PROVISIONS | S82: 0 | U82: 0 | W82: 0
B83: 1 Provizioane pentru beneficiile angajatilor (ct. 1515 + 1517) | C83: 66 | D83: PROVISIONS | F83: 0 | H83: 0 | J83: 0 | L83: 1 Provisions for employee benefits (acc. 1515 + 1517) | M83: =C83 -> 66 | N83: =F83 -> 0 | O83: =J83 -> 0 | P83: =O83-N83 -> 0 | R83: 1 Provisions for employee benefits | S83: 0 | U83: 0 | W83: 0
B84: 2 Provizioane pentru impozite (ct. 1516) | C84: 67 | D84: PROVISIONS | F84: 0 | H84: 0 | J84: 0 | L84: 2 Provisions for taxes (acc. 1516) | M84: =C84 -> 67 | N84: =F84 -> 0 | O84: =J84 -> 0 | P84: =O84-N84 -> 0 | R84: 2 Provisions for taxes | S84: 0 | U84: 0 | W84: 0
B85: 3 Alte provizioane (ct. 1511 + 1512 + 1513 + 1514 + 1518) | C85: 68 | D85: PROVISIONS | F85: 0 | H85: 0 | J85: 0 | L85: 3 Other provisions (acc. 1511 + 1512 + 1513 + 1514 + 1518) | M85: =C85 -> 68 | N85: =F85 -> 0 | O85: =J85 -> 0 | P85: =O85-N85 -> 0 | R85: 3 Other provisions | S85: 0 | U85: 0 | W85: 0
B86: TOTAL (rd. 66 + 67 + 68) | C86: 69 | F86: 0 | H86: 0 | J86: 0 | L86: TOTAL PROVISIONS (row 66, 67 and 68 ) | M86: =C86 -> 69 | N86: =F86 -> 0 | O86: =J86 -> 0 | P86: =O86-N86 -> 0 | R86: TOTAL PROVISIONS | S86: 0 | U86: 0 | W86: 0
B87: VENITURI IN AVANS | L87: INCOME IN ADVANCE | R87: INCOME IN ADVANCE | S87: 0 | U87: 0 | W87: 0
B88: 1 Subventii pentru investitii (ct. 475) (rd. 71 + 72), din care: | C88: 70 | D88: ACCRUED INCOME | F88: 0 | H88: 0 | J88: 0 | L88: 1 Investment subsidies (acc. 475) (row 71 + 72), out of which: | M88: =C88 -> 70 | N88: =F88 -> 0 | O88: =J88 -> 0 | P88: =O88-N88 -> 0 | R88: 1 Investment subsidies | S88: 0 | U88: 0 | W88: 0
B89: Sume de reluat intr-o perioada de pana la un an (din ct 475*) | C89: 71 | D89: ACCRUED INCOME | F89: 0 | H89: 0 | J89: 0 | L89: Amounts to be resumed in a period of up to one year (from acc. 475*) | M89: =C89 -> 71 | N89: =F89 -> 0 | O89: =J89 -> 0 | P89: =O89-N89 -> 0 | R89: Amounts to be resumed in a period of up to one year | S89: 0 | U89: 0 | W89: 0
B90: Sume de reluat intr-o perioada mai mare de un an (din ct 475*) | C90: 72 | D90: ACCRUED INCOME | F90: 0 | H90: 0 | J90: 0 | L90: Amounts to be resumed in a period of more than one year (from acc. 475*) | M90: =C90 -> 72 | N90: =F90 -> 0 | O90: =J90 -> 0 | P90: =O90-N90 -> 0 | R90: Amounts to be resumed in a period of more than one year | S90: 0 | U90: 0 | W90: 0
B91: 2 Venituri inregistrate in avans (ct 472) - total (rd 74 + 75), din care: | C91: 73 | D91: ACCRUED INCOME | F91: 0 | H91: 0 | J91: 0 | L91: 2 Deferred income (acc. 472) - total (row 74 + 75), out of which: | M91: =C91 -> 73 | N91: =F91 -> 0 | O91: =J91 -> 0 | P91: =O91-N91 -> 0 | R91: 2 Deferred income | S91: 0 | U91: 0 | W91: 0
B92: Sume de reluat intr-o perioada de pana la un an (ct 472*) | C92: 74 | D92: ACCRUED INCOME | F92: 0 | H92: 0 | J92: 0 | L92: Amounts to be resumed in a period of up to one year (from acc. 472*) | M92: =C92 -> 74 | N92: =F92 -> 0 | O92: =J92 -> 0 | P92: =O92-N92 -> 0 | R92: Amounts to be resumed in a period of up to one year | S92: 0 | U92: 0 | W92: 0
B93: Sume de reluat intr-o perioada mai mare de un an (ct 472*) | C93: 75 | D93: ACCRUED INCOME | F93: 0 | H93: 0 | J93: 0 | L93: Amounts to be resumed in a period of more than one year (from acc. 472*) | M93: =C93 -> 75 | N93: =F93 -> 0 | O93: =J93 -> 0 | P93: =O93-N93 -> 0 | R93: Amounts to be resumed in a period of more than one year | S93: 0 | U93: 0 | W93: 0
B94: 3 Venituri inregistrate in avans aferente activelor primite prin transfer de la clienti (ct 478) (rd 77 + 78) | C94: 76 | D94: ACCRUED INCOME | F94: 0 | H94: 0 | J94: 0 | L94: 3 Deferred revenues from assets received from transfer from clients (acc. 478) (row 77 + 78) | M94: =C94 -> 76 | N94: =F94 -> 0 | O94: =J94 -> 0 | P94: =O94-N94 -> 0 | R94: 3 Deferred revenues from assets received from transfer from clients | S94: 0 | U94: 0 | W94: 0
B95: Sume de reluat intr-o perioada de pana la un an (din ct 478*) | C95: 77 | D95: ACCRUED INCOME | F95: 0 | H95: 0 | J95: 0 | L95: Amounts to be resumed in a period of up to one year (from acc. 478*) | M95: =C95 -> 77 | N95: =F95 -> 0 | O95: =J95 -> 0 | P95: =O95-N95 -> 0 | R95: Amounts to be resumed in a period of up to one year | S95: 0 | U95: 0 | W95: 0
B96: Sume de reluat intr-o perioada mai mare de un an (din ct 478*) | C96: 78 | D96: ACCRUED INCOME | F96: 0 | H96: 0 | J96: 0 | L96: Amounts to be resumed in a period of more than one year (from acc. 478*) | M96: =C96 -> 78 | N96: =F96 -> 0 | O96: =J96 -> 0 | P96: =O96-N96 -> 0 | R96: Amounts to be resumed in a period of more than one year | S96: 0 | U96: 0 | W96: 0
B97: Fond comercial negativ (ct 2075) | C97: 79 | D97: ACCRUED INCOME | F97: 0 | H97: 0 | J97: 0 | L97: Negative goodwill (acc 2075) | M97: =C97 -> 79 | N97: =F97 -> 0 | O97: =J97 -> 0 | P97: =O97-N97 -> 0 | R97: Negative goodwill | S97: 0 | U97: 0 | W97: 0
B98: TOTAL (rd. 70 + 73 + 76 + 79) | C98: 80 | D98: ACCRUED INCOME | F98: 0 | H98: 0 | J98: 0 | L98: TOTAL (row 70 + 73 + 76 + 79) | M98: =C98 -> 80 | N98: =F98 -> 0 | O98: =J98 -> 0 | P98: =O98-N98 -> 0 | R98: TOTAL | S98: 0 | U98: 0 | W98: 0
B99: CAPITAL ȘI REZERVE | L99: CAPITAL AND RESERVES | R99: CAPITAL AND RESERVES | S99: 0 | U99: 0 | W99: 0
B100: 1 Capital subscris varsat (ct 1012) | C100: 81 | D100: EQUITY | F100: 10000 | H100: 0 | J100: 10000 | L100: 1 Subscribed and paid up share capital (acc. 1012) | M100: =C100 -> 81 | N100: =F100 -> 10000 | O100: =J100 -> 10000 | P100: =O100-N100 -> 0 | R100: 1 Subscribed and paid up share capital | S100: 2020.6102 | T100: 9.577377e-05 | U100: 2010.0503 | V100: 0.00010686501 | W100: 2010.4544 | X100: 0.00013059028
B101: 2 Capital subscris nevarsat (ct 1011) | C101: 82 | D101: EQUITY | F101: 0 | H101: 0 | J101: 0 | L101: 2 Subscribed and not paid share capital (acc. 1011) | M101: =C101 -> 82 | N101: =F101 -> 0 | O101: =J101 -> 0 | P101: =O101-N101 -> 0 | R101: 2 Subscribed and not paid share capital | S101: 0 | U101: 0 | W101: 0
...

Sheet Overview PL
B2: Original Version | K2: Original Translated Version | Q2: Steinbeis Version in €
B4: Nr. crt. | C4: Nr. rd. | E4: FY 23 | G4: ="perioada incheiata la "&TEXT('[1]SETUP INFO'!F10,"[$-418]d mmmm yyyy;@") -> perioada incheiata la d 00 yyyy | I4: FY 24 | K4: No. Description | L4: Row no. | M4: FY 23 | N4: ="for the period ended "&TEXT('[1]SETUP INFO'!F10,"[$-409]mmmm d, yyyy;@") -> for the period ended 00 d, yyyy | O4: FY 24 | Q4: No. Description | R4: FY22 | T4: FY23 | V4: FY24
B5: 1. Cifra de afaceri neta (rd. 03 + 04 - 05 + 06) | C5: 1 | E5: 186046564 | G5: 0 | I5: 169150363 | K5: 1. Net turnover (row 03 + 04 - 05 + 06) | L5: =C5 -> 1 | M5: =E5 -> 186046564 | N5: =G5 -> 0 | O5: =I5 -> 169150363 | Q5: 1. Net turnover | R5: 38216486 | S5: 0.9884008 | T5: 37396294 | U5: 0.98546718 | V5: 34006909 | W5: 0.98263516
B6: - din care cifra de afaceri neta corespunzatoare activitatii preponderente efectiv desfasurate | C6: =C5+1 -> 2 | E6: 176947139 | I6: 159646280 | K6: - out of which net turnover for the main activity | L6: =C6 -> 2 | M6: =E6 -> 176947139 | N6: =G6 -> 0 | O6: =I6 -> 159646280 | Q6: - out of which net turnover for the main activity | R6: 0 | T6: 0 | V6: 32096156
B7: - din care cifra de afaceri netă realizată din operațiuni desfășurate pe teritoriul național | C7: 2b | E7: 2307555.2 | I7: 1698652.1 | K7: - out of which, the net turnover achieved from operations carried out on national territory | L7: 2b | M7: =E7 -> 2307555.2 | N7: =G7 -> 0 | O7: =I7 -> 1698652.1 | Q7: - out of which, the net turnover achieved from operations carried out on national territory | R7: 0 | T7: 0 | V7: 341506.25
B8: Productia vanduta (ct 701 + 702 + 703 + 704 + 705 + 706 + 708 ) | C8: =C6+1 -> 3 | E8: 177341773 | G8: 0 | I8: 160152300 | K8: Sales of goods (acc. 701 + 702 + 703 + 704 + 705 + 706 + 708) | L8: =C8 -> 3 | M8: =E8 -> 177341773 | N8: =G8 -> 0 | O8: =I8 -> 160152300 | Q8: Sales of goods | R8: 36069540 | S8: 0.93287391 | T8: 0 | U8: 0 | V8: 32197889 | W8: 0.93036324
B9: Venituri din vanzarea marfurilor (ct 707 ) | C9: 4 | E9: 8704791 | G9: 0 | I9: 8998063 | K9: Sales of merchandise (acc. 707) | L9: =C9 -> 4 | M9: =E9 -> 8704791 | N9: =G9 -> 0 | O9: =I9 -> 8998063 | Q9: Sales of merchandise | R9: 2146945.6 | S9: 0.055526895 | T9: 0 | U9: 0 | V9: 1809019.5 | W9: 0.052271913
B10: Reduceri comerciale acordate (ct 709) | C10: 5 | E10: 0 | G10: 0 | I10: 0 | K10: Discounts granted (acc. 709) | L10: =C10 -> 5 | M10: =E10 -> 0 | N10: =G10 -> 0 | O10: =I10 -> 0 | Q10: Discounts granted | R10: 0 | T10: 0 | V10: 0
B11: Venituri din subventii de exploatare aferente cifrei de afaceri nete (ct 7411) | C11: 6 | E11: 0 | G11: 0 | I11: 0 | K11: Revenue from operating subsidies related to the turnover (acc. 7411) | L11: =C11 -> 6 | M11: =E11 -> 0 | N11: =G11 -> 0 | O11: =I11 -> 0 | Q11: Revenue from operating subsidies related to the turnover | R11: 0 | T11: 0 | V11: 0
B12: 2. Venituri aferente costului productiei in curs de executie(ct 711+712) - Sold C | C12: 7 | E12: 0 | G12: 0 | I12: 0 | K12: 2. Revenue related to the cost of the work in progress (acc. 711+712) - Cr Balance | L12: =C12 -> 7 | M12: =E12 -> 0 | N12: =G12 -> 0 | O12: =I12 -> 0 | Q12: 2. Revenue related to the cost of the work in progress | R12: 0 | T12: 0 | V12: 0
B13: Venituri aferente costului productiei in curs de executie(ct 711+712) - Sold D | C13: 8 | E13: 0 | G13: 0 | I13: 0 | K13: Revenue related to the cost of the work in progress (acc. 711 + 712) - Dr Balance | L13: =C13 -> 8 | M13: =E13 -> 0 | N13: =G13 -> 0 | O13: =I13 -> 0 | Q13: Revenue related to the cost of the work in progress | R13: 0 | T13: 0 | V13: 0
B14: 3. Venituri din productia de imobilizari necorporale si corporale (ct 721 + 722) | C14: 9 | E14: 0 | G14: 0 | I14: 0 | K14: 3. Income from production of tangible and intangible assets (acc. 721 + 722) | L14: =C14 -> 9 | M14: =E14 -> 0 | N14: =G14 -> 0 | O14: =I14 -> 0 | Q14: 3. Income from production of tangible and intangible assets | R14: 0 | T14: 0 | V14: 0
B15: 4. Venituri din reevaluarea imobilizarilor corporale (ct 755) | C15: 10 | E15: 0 | G15: 0 | I15: 0 | K15: 4. Income from the revaluation of tangible assets (acc. 755) | L15: =C15 -> 10 | M15: =E15 -> 0 | N15: =G15 -> 0 | O15: =I15 -> 0 | Q15: 4. Income from the revaluation of tangible assets | R15: 0 | T15: 0 | V15: 0
B16: 5. Venituri din productia de investitii imobiliare (ct 725) | C16: 11 | E16: 0 | G16: 0 | I16: 0 | K16: 5. Income from production of real estate investments (acc. 725) | L16: =C16 -> 11 | M16: =E16 -> 0 | N16: =G16 -> 0 | O16: =I16 -> 0 | Q16: 5. Income from production of real estate investments | R16: 0 | T16: 0 | V16: 0
B17: 6. Venituri din subventii de exploatare (ct 7412 + 7413 + 7414 + 7415 +7416 + 7417 + 7419) | C17: 12 | E17: 0 | G17: 0 | I17: 0 | K17: 6. Income from operating subsidies (acc. 7412 + 7413 + 7414 + 7415 + 7416 + 7417 + 7419) | L17: =C17 -> 12 | M17: =E17 -> 0 | N17: =G17 -> 0 | O17: =I17 -> 0 | Q17: 6. Income from operating subsidies | R17: 0 | T17: 0 | V17: 0
B18: 7. Alte venituri din exploatare (ct 751 + 758 + 7815) | C18: 13 | E18: 2743654 | G18: 0 | I18: 2989176 | K18: 7. Other operating income (acc. 751 + 758 + 7815) | L18: =C18 -> 13 | M18: =E18 -> 2743654 | N18: =G18 -> 0 | O18: =I18 -> 2989176 | Q18: 7. Other operating income | R18: 448482.52 | S18: 0.011599195 | T18: 551488.24 | U18: 0.014532819 | V18: 600960.19 | W18: 0.017364843
B19: - din care, venituri din subventii pentru investitii (ct 7584) | C19: 14 | E19: 0 | G19: 0 | I19: 0 | K19: - out of which, income from investment subsidies (acc. 7584) | L19: =C19 -> 14 | M19: =E19 -> 0 | N19: =G19 -> 0 | O19: =I19 -> 0 | Q19: - out of which, income from investment subsidies | R19: 6159.6282 | S19: 0.00015930773 | T19: 0 | V19: 0
B20: - din care, venituri din fondul comercial negativ (ct 7815) | C20: 15 | E20: 0 | G20: 0 | I20: 0 | K20: - out of which, income from negative goodwill (acc. 7815) | L20: =C20 -> 15 | M20: =E20 -> 0 | N20: =G20 -> 0 | O20: =I20 -> 0 | Q20: - out of which, income from negative goodwill | R20: 0 | T20: 0 | V20: 0
B21: VENITURI DIN EXPLOATARE - TOTAL (rd. 01+07-08+09+10+11+12+13) | C21: 16 | E21: 188790218 | G21: 0 | I21: 172139539 | K21: OPERATING INCOME – TOTAL (rows 01 + 07 – 08 + 09 + 10 + 11 + 12 + 13) | L21: =C21 -> 16 | M21: =E21 -> 188790218 | N21: =G21 -> 0 | O21: =I21 -> 172139539 | Q21: OPERATING INCOME – TOTAL | R21: 38664968 | S21: 1.0001593 | T21: 37947783 | U21: 0.014532819 | V21: 34607869 | W21: 1
B22: 8. a) Cheltuieli cu materiile prime si materialele consumabile (ct 601 + 602) | C22: 17 | E22: 32409315 | G22: 0 | I22: 28691875 | K22: 8. a) Expenses related to raw materials and consumables (acc. 601 + 602) | L22: =C22 -> 17 | M22: =E22 -> 32409315 | N22: =G22 -> 0 | O22: =I22 -> 28691875 | Q22: 8. a) Expenses related to raw materials and consumables | R22: 6764286.9 | S22: 0.17494614 | T22: 6514435.2 | U22: 0.1716684 | V22: 5768370.5 | W22: 0.16667801
B23: Alte cheltuieli materiale (ct 603 + 604 + 606 + 608) | C23: 18 | E23: 165212 | G23: 0 | I23: 108982 | K23: Other material expenses (acc. 603 + 604 + 606 + 608) | L23: =C23 -> 18 | M23: =E23 -> 165212 | N23: =G23 -> 0 | O23: =I23 -> 108982 | Q23: Other material expenses | R23: 30171.752 | S23: 0.0007803382 | T23: 33208.442 | U23: 0.0008751089 | V23: 21910.334 | W23: 0.00063310266
B24: b) Alte cheltuieli externe (cu energie si apa) (ct 605) | C24: 19 | E24: 304137 | G24: 0 | I24: 202518 | K24: b) Other external expenses (power and water supply) (acc. 605) | L24: =C24 -> 19 | M24: =E24 -> 304137 | N24: =G24 -> 0 | O24: =I24 -> 202518 | Q24: b) Other external expenses (power and water supply) | R24: 86376.44 | S24: 0.0022339716 | T24: 61133.065 | U24: 0.0016109786 | V24: 40715.32 | W24: 0.0011764758
B25: din care, cheltuieli privind consumul de energie(ct.6051) | C25: 20 | E25: 292980 | G25: 0 | I25: 185075 | K25: - out of which, expenses with power consumption (acc. 6051) | L25: =C25 -> 20 | M25: =E25 -> 292980 | N25: =G25 -> 0 | O25: =I25 -> 185075 | Q25: - out of which, expenses with power consumption | R25: 84990.099 | S25: 0.0021981163 | T25: 58890.452 | U25: 0.0015518813 | V25: 37208.484 | W25: 0.0010751452
B26: din care, cheltuieli privind consumul de gaze naturale(ct.6053) | C26: 21 | E26: 0 | G26: 0 | I26: 0 | K26: - out of which, expenses with natural gas consumption (acc. 6053) | L26: =C26 -> 21 | M26: =E26 -> 0 | N26: =G26 -> 0 | O26: =I26 -> 0 | Q26: - out of which, expenses with natural gas consumption | R26: 0 | T26: 0 | V26: 0
B27: c) Cheltuieli privind marfurile (ct 607) | C27: 22 | E27: 8700332 | G27: 0 | I27: 8997248 | K27: c) Merchandise expenses (acc. 607) | L27: =C27 -> 22 | M27: =E27 -> 8700332 | N27: =G27 -> 0 | O27: =I27 -> 8997248 | Q27: c) Merchandise expenses | R27: 2145422.1 | S27: 0.055487491 | T27: 1748810.5 | U27: 0.046084655 | V27: 1808855.6 | W27: 0.052267178
B28: Reduceri comerciale primite (ct 609) | C28: 23 | E28: 0 | G28: 0 | I28: 0 | K28: Commercial discounts received (acc. 609) | L28: =C28 -> 23 | M28: =E28 -> 0 | N28: =G28 -> 0 | O28: =I28 -> 0 | Q28: Commercial discounts received | R28: 0 | T28: 0 | V28: 0
B29: 9. Cheltuieli cu personalul (rd. 25+26) | C29: 24 | E29: 20738502 | G29: 0 | I29: 21306331 | K29: 9. Personnel expenses (rows 25 + 26), out of which: | L29: =C29 -> 24 | M29: =E29 -> 20738502 | N29: =G29 -> 0 | O29: =I29 -> 21306331 | Q29: 9. Personnel expenses | R29: 3420668.4 | S29: 0.088469448 | T29: 4168543.1 | U29: 0.10984945 | V29: 4283540.6 | W29: 0.1237736
B30: a) Salarii si indemnizatii (ct 641 + 642 + 643 + 644) | C30: 25 | E30: 20293964 | G30: 0 | I30: 20834115 | K30: a) Salaries and allowance (acc. 641 + 642 + 643 + 644) | L30: =C30 -> 25 | M30: =E30 -> 20293964 | N30: =G30 -> 0 | O30: =I30 -> 20834115 | Q30: a) Salaries and allowance | R30: 3347551.6 | S30: 0.086578413 | T30: 4079188.7 | U30: 0.10749479 | V30: 4188603.7 | W30: 0.12103039
B31: b) Cheltuieli cu asigurarile si protectia sociala (ct 645+646) | C31: 26 | E31: 444538 | G31: 0 | I31: 472216 | K31: b) Social security (acc. 645 + 646) | L31: =C31 -> 26 | M31: =E31 -> 444538 | N31: =G31 -> 0 | O31: =I31 -> 472216 | Q31: b) Social security | R31: 73116.791 | S31: 0.0018910346 | T31: 89354.372 | U31: 0.0023546665 | V31: 94936.872 | W31: 0.0027432164
B32: 10. a) Ajustari de valoare privind imobilizarile corporale si necorporale (rd. 28+-29-30) | C32: 27 | E32: 14479166 | G32: 0 | I32: 12445466 | K32: 10. a) Value adjustments regarding tangible and intangible assets (rows 28+29-30) | L32: =C32 -> 27 | M32: =E32 -> 14479166 | N32: =G32 -> 0 | O32: =I32 -> 12445466 | Q32: 10. a) Value adjustments regarding tangible and intangible assets | R32: 2860043.2 | S32: 0.073969884 | T32: 2910385.1 | U32: 0.076694472 | V32: 2502104.1 | W32: 0.072298706
B33: a. 1) Cheltuieli de exploatare privind amortizarea imobilizarilor (ct. 6811) | C33: 28 | E33: 14479166 | G33: 0 | I33: 12445466 | K33: a. 1) Expenses with depreciation and amortisation (acc. 6811) | L33: =C33 -> 28 | M33: =E33 -> 14479166 | N33: =G33 -> 0 | O33: =I33 -> 12445466 | Q33: a. 1) Expenses with depreciation and amortisation | R33: 2860043.2 | S33: 0.073969884 | T33: 2910385.1 | U33: 0.076694472 | V33: 2502104.1 | W33: 0.072298706
B34: a. 2) Alte cheltuieli (ct 6813 + 6817+ din ct 6818) | C34: 29 | E34: 0 | G34: 0 | I34: 0 | K34: a. 2) Other expenses (acc. 6813 + 6817+ from acc. 6818) | L34: =C34 -> 29 | M34: =E34 -> 0 | N34: =G34 -> 0 | O34: =I34 -> 0 | Q34: a. 2) Other expenses | R34: 0 | T34: 0 | V34: 0
B35: a. 3) Venituri (ct 7813+ din ct.7818) | C35: 30 | E35: 0 | G35: 0 | I35: 0 | K35: a. 3) Income (acc. 7813 + from acc. 7818) | L35: =C35 -> 30 | M35: =E35 -> 0 | N35: =G35 -> 0 | O35: =I35 -> 0 | Q35: a. 3) Income | R35: 0 | T35: 0 | V35: 0
B36: b) Ajustari de valoare privind activele circulante (rd. 31-32) | C36: 31 | E36: -32931 | G36: 0 | I36: 181561 | K36: 10. b) Value adjustments regarding current assets (rows 31 – 32) | L36: =C36 -> 31 | M36: =E36 -> -32931 | N36: =G36 -> 0 | O36: =I36 -> 181561 | Q36: 10. b) Value adjustments regarding current assets | R36: 1497.2722 | S36: 3.8724257e-05 | T36: -6619.2965 | U36: -0.00017443171 | V36: 36502.01 | W36: 0.0010547315
B37: b. 1) Cheltuieli (ct 654 + 6814 + din ct.6818) | C37: 32 | E37: 40085 | G37: 0 | I37: 241919 | K37: b. 1) Expenses (acc. 654 + 6814 + from acc. 6818) | L37: =C37 -> 32 | M37: =E37 -> 40085 | N37: =G37 -> 0 | O37: =I37 -> 241919 | Q37: b. 1) Expenses | R37: 60289.351 | S37: 0.0015592758 | T37: 8057.2864 | U37: 0.00021232562 | V37: 48636.711 | W37: 0.0014053657
B38: b. 2) Venituri (ct 754 + 7814+ din ct.7818) | C38: 33 | E38: 73016 | G38: 0 | I38: 60358 | K38: b. 2) Income (acc. 754 + 7814 + from acc. 7818) | L38: =C38 -> 33 | M38: =E38 -> 73016 | N38: =G38 -> 0 | O38: =I38 -> 60358 | Q38: b. 2) Income | R38: 58792.079 | S38: 0.0015205516 | T38: 14676.583 | U38: 0.00038675733 | V38: 12134.7 | W38: 0.00035063414
B39: 11. Alte cheltuieli de exploatare (rd. 35 + 36 + 40 + 42 + 44 + 46 + 47 + 48 + 49 + 50) | C39: 34 | E39: 103349844 | G39: 0 | I39: 97460549 | K39: 11. Other operating expenses (rows 35 + 36 + 40 + 42 + 44 + 46 + 47 + 48 + 49 + 50) | L39: =C39 -> 34 | M39: =E39 -> 103349844 | N39: =G39 -> 0 | O39: =I39 -> 97460549 | Q39: 11. Other operating expenses | R39: 20860357 | S39: 0.53951993 | T39: 20773838 | U39: 0.5474322 | V39: 19593999 | W39: 0.56617178
B40: 11.1. Cheltuieli privind prestatiile externe (ct 611 + 613 + 614 + 615 + 621 + 622 + 623 + 624 + 625 + 626 + 627 + 628) | C40: 35 | E40: 99985334 | G40: 0 | I40: 95276172 | K40: 11.1. External services expenses (acc. 611 + 613 + 614 + 615 + 621 + 622 + 623 + 624 + 625 + 626 + 627 + 628) | L40: =C40 -> 35 | M40: =E40 -> 99985334 | N40: =G40 -> 0 | O40: =I40 -> 95276172 | Q40: 11.1. External services expenses | R40: 20609084 | S40: 0.53301695 | T40: 20097555 | U40: 0.52961078 | V40: 19154840 | W40: 0.55348221
B41: 11.2. Cheltuieli cu redeventele, locatiile de gestiune si chiriile (ct 612) | C41: 36 | E41: 174978 | F41: 0 | G41: 0 | I41: 425184 | K41: 11.2.Expenses with Royalties, management leases and rental (acc. 612) | L41: =C41 -> 36 | M41: =E41 -> 174978 | N41: =G41 -> 0 | O41: =I41 -> 425184 | Q41: 11.2.Expenses with Royalties, management leases and rental | R41: 164.07355 | S41: 4.2434678e-06 | T41: 35171.457 | U41: 0.00092683828 | V41: 85481.303 | W41: 0.0024699962
B42: - cheltuieli cu redevente (ct. 6121) | C42: 37 | E42: 0 | G42: 0 | I42: 0 | K42: - Expenses with Royalties (acc. 6121) | M42: =E42 -> 0 | N42: =G42 -> 0 | O42: =I42 -> 0 | Q42: - Expenses with Royalties | R42: 0 | T42: 0 | V42: 0
B43: - cheltuieli cu locațiile de gestiune (ct. 6122) | C43: 38 | E43: 0 | G43: 0 | I43: 0 | K43: - Expenses with Management leases (acc. 6122) | M43: =E43 -> 0 | N43: =G43 -> 0 | O43: =I43 -> 0 | Q43: - Expenses with Management leases | R43: 0 | T43: 0 | V43: 0
B44: - cheltuieli cu chiriile (ct. 6123) | C44: 39 | E44: 174978 | G44: 0 | I44: 425184 | K44: - Expenses with Rent expenses (acc. 6123) | M44: =E44 -> 174978 | N44: =G44 -> 0 | O44: =I44 -> 425184 | Q44: - Expenses with Rent expenses | R44: 164.07355 | S44: 4.2434678e-06 | T44: 35171.457 | U44: 0.00092683828 | V44: 85481.303 | W44: 0.0024699962
B45: 11.3. Cheltuieli aferente drepturilor de proprietate intelectuala (ct. 616) | C45: 40 | E45: 0 | G45: 0 | I45: 0 | K45: 11.2.Expenses with Intellectual property rights (acc. 616) | M45: =E45 -> 0 | N45: =G45 -> 0 | O45: =I45 -> 0 | Q45: 11.2.Expenses with Intellectual property rights | R45: 0 | T45: 0 | V45: 0
B46: - din care, cheltuieli in relatia cu entitatile afiliate | C46: 41 | K46: - of which, expenses related to affiliates | M46: =E46 -> 0 | N46: =G46 -> 0 | O46: =I46 -> 0 | Q46: - of which, expenses related to affiliates | R46: 0 | T46: 0 | V46: 0
B47: 11.4. Cheltuieli de management (ct. 617) | C47: 42 | E47: 0 | G47: 0 | I47: 0 | K47: 11.4. Expenses with management (acc. 617*) | L47: =C47 -> 42 | M47: =E47 -> 0 | N47: =G47 -> 0 | O47: =I47 -> 0 | Q47: 11.4. Expenses with management | R47: 0 | T47: 0 | V47: 0
B48: - din care, cheltuieli in relatia cu entitatile afiliate | C48: 43 | K48: - of which, expenses related to affiliates | L48: =C48 -> 43 | M48: =E48 -> 0 | N48: =G48 -> 0 | O48: =I48 -> 0 | Q48: - of which, expenses related to affiliates | R48: 0 | T48: 0 | V48: 0
B49: 11.5. Cheltuieli de consultanta (ct. 618) | C49: 44 | E49: 0 | G49: 0 | I49: 0 | K49: 11.5. Expenses with consulting (acc. 618) | M49: =E49 -> 0 | N49: =G49 -> 0 | O49: =I49 -> 0 | Q49: 11.5. Expenses with consulting | R49: 0 | T49: 0 | V49: 0
B50: - din care, cheltuieli in relatia cu entitatile afiliate | C50: 45 | K50: - of which, expenses related to affiliates | M50: =E50 -> 0 | N50: =G50 -> 0 | O50: =I50 -> 0 | Q50: - of which, expenses related to affiliates | R50: 0 | T50: 0 | V50: 0
B51: 11.6. Cheltuieli cu alte impozite, taxe si varsaminte asimilate; cheltuieli reprezentand transferuri si contributii datorate in baza unor acte normative speciale (ct. 635 + 6586*) | C51: 46 | E51: 536849 | G51: 0 | I51: 631644 | K51: 11.6. Expenses with other taxes, charges and similar expenses; Transfers and contributions owed based on special acts of legislation (acc. 635 + 6586) | M51: =E51 -> 536849 | N51: =G51 -> 0 | O51: =I51 -> 631644 | Q51: 11.6. Expenses with other taxes, charges and similar expenses; Transfers and contributions owed based on special acts of legislation | R51: 101415.24 | S51: 0.002622923 | T51: 107909.35 | U51: 0.0028436272 | V51: 126989.14 | W51: 0.003669372
B52: 11.7. Cheltuieli cu protectia mediului inconjurator (ct 652) | C52: 47 | E52: 0 | G52: 0 | I52: 0 | K52: 11.7. Expenses with environmental protection (acc. 652) | M52: =E52 -> 0 | N52: =G52 -> 0 | O52: =I52 -> 0 | Q52: 11.7. Expenses with environmental protection | R52: 0 | T52: 0 | V52: 0
B53: 11.8. Cheltuieli din reevaluarea imobilizarilor corporale (ct 655) | C53: 48 | E53: 0 | G53: 0 | I53: 0 | K53: 11.8. Expenses related to revaluation of tangible assets (acc. 655) | L53: =C53 -> 48 | M53: =E53 -> 0 | N53: =G53 -> 0 | O53: =I53 -> 0 | Q53: 11.8. Expenses related to revaluation of tangible assets | R53: 0 | T53: 0 | V53: 0
B54: 11.9. Cheltuieli privind calamitatile si alte evenimente similare (ct 6587) | C54: 49 | E54: 0 | G54: 0 | I54: 0 | K54: 11.9. Expenses related to natural disasters and other similar events (acc. 6587) | L54: =C54 -> 49 | M54: =E54 -> 0 | N54: =G54 -> 0 | O54: =I54 -> 0 | Q54: 11.9. Expenses related to natural disasters and other similar events | R54: 0 | T54: 0 | V54: 0
B55: 11.10. Alte cheltuieli (ct 651 + 6581 + 6582 + 6583 +6584+ 6588) | C55: 50 | E55: 2652683 | G55: 0 | I55: 1127549 | K55: 11.10. Other expenses (acc. 651 + 6581 + 6582 + 6583 + 6584 + 6588) | L55: =C55 -> 50 | M55: =E55 -> 2652683 | N55: =G55 -> 0 | O55: =I55 -> 1127549 | Q55: 11.10. Other expenses | R55: 149693.88 | S55: 0.0038715634 | T55: 533202.61 | U55: 0.014050956 | V55: 226688.58 | W55: 0.0065502034
B56: 12. Ajustari privind provizioanele (rd. 52-53) | C56: 51 | E56: 0 | G56: 0 | I56: 0 | K56: 12. Adjustments regarding the provisions (rows 52 – 53) | L56: =C56 -> 51 | M56: =E56 -> 0 | N56: =G56 -> 0 | O56: =I56 -> 0 | Q56: 12. Adjustments regarding the provisions | R56: 0 | T56: 0 | V56: 0 | W56: 0
B57: - Cheltuieli (ct 6812) | C57: 52 | E57: 0 | G57: 0 | I57: 0 | K57: - Expenses (acc. 6812) | L57: =C57 -> 52 | M57: =E57 -> 0 | N57: =G57 -> 0 | O57: =I57 -> 0 | Q57: - Expenses | R57: 0 | T57: 0 | V57: 0
B58: - Venituri (ct 7812) | C58: 53 | E58: 0 | G58: 0 | I58: 0 | K58: - Income (acc. 7812) | L58: =C58 -> 53 | M58: =E58 -> 0 | N58: =G58 -> 0 | O58: =I58 -> 0 | Q58: - Income | R58: 0 | T58: 0 | V58: 0
B59: CHELTUIELI DE EXPLOATARE - TOTAL (rd. 17 + 18 + 19 + 22 – 23 + 24 + 27 + 31 + 34 + 51) | C59: 54 | E59: 180113577 | G59: 0 | I59: 169394530 | K59: OPERATING EXPENSES – TOTAL (rows 17 + 18 + 19 + 22 – 23 + 24 + 27 + 31 + 34 + 51) | L59: =C59 -> 54 | M59: =E59 -> 180113577 | N59: =G59 -> 0 | O59: =I59 -> 169394530 | Q59: OPERATING EXPENSES – TOTAL | R59: 36168823 | S59: 0.93544168 | T59: 36203734 | U59: 0.95404083 | V59: 34055997 | W59: 0.98405358
B60: PROFITUL SAU PIERDEREA DIN EXPLOATARE | K60: OPERATING PROFIT OR LOSS | N60: =G60 -> 0 | Q60: OPERATING PROFIT OR LOSS | R60: 0 | T60: 0 | V60: 0
B61: - Profit (rd. 16 - 54) | C61: 55 | E61: 8676641 | G61: 0 | I61: 2745009 | K61: - Profit (rows 16 – 54) | L61: =C61 -> 55 | M61: =E61 -> 8676641 | N61: =G61 -> 0 | O61: =I61 -> 2745009 | Q61: - Profit | R61: 2496145.5 | S61: 0.064558322 | T61: 1744048.4 | U61: 0.045959166 | V61: 551871.53 | W61: 0.015946418
B62: - Pierdere (rd. 54 - 16) | C62: 56 | E62: 0 | G62: 0 | I62: 0 | K62: - Loss (rows 54 – 16) | L62: =C62 -> 56 | M62: =E62 -> 0 | N62: =G62 -> 0 | O62: =I62 -> 0 | Q62: - Loss | R62: 0 | T62: 0 | V62: 0
B63: 13. Venituri din interese de participare (ct 7611 + 7612 + 7613) | C63: 57 | E63: 0 | G63: 0 | I63: 0 | K63: 13. Income from participating interests (acc. 7611 + 7612 + 7613) | L63: =C63 -> 57 | M63: =E63 -> 0 | N63: =G63 -> 0 | O63: =I63 -> 0 | Q63: 13. Income from participating interests | R63: 0 | T63: 0 | V63: 0
B64: - din care, veniturile obtinute de la entitati afiliate | C64: 58 | K64: of which, income from affiliates | L64: =C64 -> 58 | M64: =E64 -> 0 | N64: =G64 -> 0 | O64: =I64 -> 0 | Q64: - of which, income from affiliates | R64: 0 | T64: 0 | V64: 0
B65: 14. Venituri din dobanzi (ct 766) | C65: 59 | E65: 1158914 | G65: 0 | I65: 1136183 | K65: 14. Interest income (acc. 766) | L65: =C65 -> 59 | M65: =E65 -> 1158914 | N65: =G65 -> 0 | O65: =I65 -> 1136183 | Q65: 14. Interest income | R65: 73234.189 | S65: 0.0018940708 | T65: 232947.54 | U65: 0.0061386337 | V65: 228424.41 | W65: 0.0066003604
B66: - din care, veniturile obtinute de la entitati afiliate | C66: 60 | E66: 1042413 | I66: 973283 | K66: - of which, income from affiliates | L66: =C66 -> 60 | M66: =E66 -> 1042413 | N66: =G66 -> 0 | O66: =I66 -> 973283 | Q66: - of which, income from affiliates | R66: 21972.396 | S66: 0.00056827659 | T66: 209530.25 | U66: 0.0055215414 | V66: 195674.11 | W66: 0.0056540351
B67: 15. Venituri din subventii de exploatare pentru dobanda datorata (ct 7418) | C67: 61 | E67: 0 | G67: 0 | I67: 0 | K67: 15. Income from operating subsidies for interest payable (acc. 7418) | L67: =C67 -> 61 | M67: =E67 -> 0 | N67: =G67 -> 0 | O67: =I67 -> 0 | Q67: 15. Income from operating subsidies for interest payable | R67: 0 | T67: 0 | V67: 0
B68: 16. Alte venituri financiare (ct 7615 + 762 + 764 + 765 + 767 + 768) | C68: 62 | E68: 2696216 | G68: 0 | I68: 909264 | K68: 16. Other financial income (acc. 7615 + 762 + 764 + 765 + 767 + 768) | L68: =C68 -> 62 | M68: =E68 -> 2696216 | N68: =G68 -> 0 | O68: =I68 -> 909264 | Q68: 16. Other financial income | R68: 506588.4 | S68: 0.013102 | T68: 541952.96 | U68: 0.014281545 | V68: 182803.38 | W68: 0.0052821334
B69: - din care, venituri din imobilizari financiare (ct 7615) | C69: 63 | E69: 0 | G69: 0 | I69: 0 | K69: - of which, income from financial assets (acc. 7615) | L69: =C69 -> 63 | M69: =E69 -> 0 | N69: =G69 -> 0 | O69: =I69 -> 0 | Q69: - of which, income from financial assets | R69: 0 | T69: 0 | V69: 0
B70: VENITURI FINANCIARE - TOTAL (rd. 57 + 59 + 61 + 62) | C70: 64 | E70: 3855130 | G70: 0 | I70: 2045447 | K70: FINANCIAL INCOME – TOTAL (rows 57 + 59 + 61 + 62) | L70: =C70 -> 64 | M70: =E70 -> 3855130 | N70: =G70 -> 0 | O70: =I70 -> 2045447 | Q70: FINANCIAL INCOME – TOTAL | R70: 579822.59 | S70: 0.01499607 | T70: 774900.5 | U70: 0.020420179 | V70: 411227.78 | W70: 0.011882494
B71: 17. Ajustari de valoare privind imobilizarile financiare si investitiile detinute ca active circulante (rd. 66-67) | C71: 65 | E71: 0 | G71: 0 | I71: 0 | K71: 17. Value adjustments regarding the financial assets and financial investments held as current assets (rows 66-67) | L71: =C71 -> 65 | M71: =E71 -> 0 | N71: =G71 -> 0 | O71: =I71 -> 0 | Q71: 17. Value adjustments regarding the financial assets and financial investments held as current assets | R71: 0 | T71: 0 | V71: 0 | W71: 0
B72: - Cheltuieli (ct 686) | C72: 66 | E72: 0 | G72: 0 | I72: 0 | K72: Expenses (acc. 686) | L72: =C72 -> 66 | M72: =E72 -> 0 | N72: =G72 -> 0 | O72: =I72 -> 0 | Q72: Expenses | R72: 0 | T72: 0 | V72: 0
B73: - Venituri (ct 786) | C73: 67 | E73: 0 | G73: 0 | I73: 0 | K73: Income (acc. 786) | L73: =C73 -> 67 | M73: =E73 -> 0 | N73: =G73 -> 0 | O73: =I73 -> 0 | Q73: Income | R73: 0 | T73: 0 | V73: 0
B74: 18. Cheltuieli privind dobanzile (ct 666*) | C74: 68 | E74: 2025963 | G74: 0 | I74: 1659717 | K74: 18. Interest expenses (acc. 666*) | L74: =C74 -> 68 | M74: =E74 -> 2025963 | N74: =G74 -> 0 | O74: =I74 -> 1659717 | Q74: 18. Interest expenses | R74: 281040.01 | S74: 0.0072685953 | T74: 407228.74 | U74: 0.010731292 | V74: 333678.53 | W74: 0.0096416954
B75: - din care, cheltuieli in relatie cu entitati afiliate | C75: 69 | K75: - of which, expenses related to affiliates | L75: =C75 -> 69 | M75: =E75 -> 0 | N75: =G75 -> 0 | O75: =I75 -> 0 | Q75: - of which, expenses related to affiliates | R75: 465.34653 | S75: 1.2035353e-05 | T75: 0 | V75: 0
B76: 19. Alte cheltuieli financiare (ct 663 + 664 + 665 + 667 + 668) | C76: 70 | E76: 2735857 | G76: 0 | I76: 684219 | K76: 19. Other financial expenses (acc. 663 + 664 + 665 + 667 + 668) | L76: =C76 -> 70 | M76: =E76 -> 2735857 | N76: =G76 -> 0 | O76: =I76 -> 684219 | Q76: 19. Other financial expenses | R76: 455423.12 | S76: 0.011778701 | T76: 549921.01 | U76: 0.014491519 | V76: 137559.11 | W76: 0.0039747928
B77: CHELTUIELI FINANCIARE - TOTAL (rd. 65 + 68 + 70) | C77: 71 | E77: 4761820 | G77: 0 | I77: 2343936 | K77: FINANCIAL EXPENSES – TOTAL (rows 65 + 68 + 70) | L77: =C77 -> 71 | M77: =E77 -> 4761820 | N77: =G77 -> 0 | O77: =I77 -> 2343936 | Q77: FINANCIAL EXPENSES – TOTAL | R77: 736463.12 | S77: 0.019047297 | T77: 957149.75 | U77: 0.025222811 | V77: 471237.64 | W77: 0.013616488
B78: - Profit (rd. 64 – 71) | C78: 72 | E78: 0 | G78: 0 | I78: 0 | K78: - Profit (row 64 – 71) | L78: =C78 -> 72 | M78: =E78 -> 0 | N78: =G78 -> 0 | O78: =I78 -> 0 | Q78: - Profit | R78: 0 | T78: 0 | V78: 0
B79: - Pierdere (rd. 71 – 64) | C79: 73 | E79: 906690 | G79: 0 | I79: 298489 | K79: - Loss (row 71 – 64) | L79: =C79 -> 73 | M79: =E79 -> 906690 | N79: =G79 -> 0 | O79: =I79 -> 298489 | Q79: - Loss | R79: 156640.53 | S79: 0.0040512262 | T79: 182249.25 | U79: 0.0048026323 | V79: 60009.851 | W79: 0.0017339944
B80: VENITURI TOTALE (rd 16 + 64) | C80: 74 | E80: 192645348 | G80: 0 | I80: 174184986 | K80: TOTAL INCOME (rows 16 + 64) | L80: =C80 -> 74 | M80: =E80 -> 192645348 | N80: =G80 -> 0 | O80: =I80 -> 174184986 | Q80: TOTAL INCOME | R80: 39244791 | S80: 1.0149961 | T80: 38722683 | U80: 1.0204202 | V80: 35019097 | W80: 1.0118825
B81: CHELTUIELI TOTALE (rd 54 + 71) | C81: 75 | E81: 184875397 | G81: 0 | I81: 171738466 | K81: TOTAL EXPENSES (rows 54 + 71) | L81: =C81 -> 75 | M81: =E81 -> 184875397 | N81: =G81 -> 0 | O81: =I81 -> 171738466 | Q81: TOTAL EXPENSES | R81: 36905286 | S81: 0.95448897 | T81: 37160884 | U81: 0.97926364 | V81: 34527235 | W81: 0.99767007
B82: PROFITUL SAU PIERDEREA BRUT(A) | K82: GROSS PROFIT OR LOSS | M82: =E82 -> 0 | N82: =G82 -> 0 | O82: =I82 -> 0 | Q82: GROSS PROFIT OR LOSS | R82: 0 | T82: 0 | V82: 0
B83: - Profit (rd. 74 - 75) | C83: 76 | E83: 7769951 | G83: 0 | I83: 2446520 | K83: - Profit (row 74 - 75) | L83: =C83 -> 76 | M83: =E83 -> 7769951 | N83: =G83 -> 0 | O83: =I83 -> 2446520 | Q83: - Profit | R83: 2339505 | S83: 0.060507096 | T83: 1561799.2 | U83: 0.041156534 | V83: 491861.68 | W83: 0.014212423
B84: - Pierdere (rd. 75 - 74) | C84: 77 | E84: 0 | G84: 0 | I84: 0 | K84: - Loss (row 75 - 74) | L84: =C84 -> 77 | M84: =E84 -> 0 | N84: =G84 -> 0 | O84: =I84 -> 0 | Q84: - Loss | R84: 0 | T84: 0 | V84: 0
B85: 20. IMPOZITUL PE PROFIT (ct 691) | C85: 78 | E85: 1346234 | G85: 0 | I85: 657346 | K85: 20. Income Tax (acc. 691) | L85: =C85 -> 78 | M85: =E85 -> 1346234 | N85: =G85 -> 0 | O85: =I85 -> 657346 | Q85: 20. Income Tax | R85: 364367.75 | S85: 0.0094237178 | T85: 270599.8 | U85: 0.0071308462 | V85: 132156.41 | W85: 0.0038186811
L86: =C86 -> 0 | M86: =E86 -> 0 | N86: =G86 -> 0 | O86: =I86 -> 0 | R86: 0 | T86: 0 | V86: 0
B87: 21. Cheltuieli cu impozitul pe profit, respectiv impozitul pe profit la nivelul impozitului minim pe cifra de afaceri, rezultat din decontările în cadrul grupului fiscal în domeniul impozitului pe profit(ct.694) | C87: 79 | E87: 0 | G87: 0 | I87: 0 | K87: 21. Expenses with income tax, including minimum turnover tax, resulting from income tax settlements in the tax group (acc. 694) | L87: =C87 -> 79 | M87: =E87 -> 0 | N87: =G87 -> 0 | O87: =I87 -> 0 | Q87: 21. Expenses with income tax, including minimum turnover tax, resulting from income tax settlements in the tax group | R87: 0 | T87: 0 | V87: 0
L88: =C88 -> 0 | M88: =E88 -> 0 | N88: =G88 -> 0 | O88: =I88 -> 0 | R88: 0 | T88: 0 | V88: 0
B89: 22. Venituri din impozitul pe profit rezultat din decontarule in cadrul grupului fiscal in domeniul impozitului pe profit (ct. 794) | C89: 80 | E89: 0 | G89: 0 | I89: 0 | K89: 22. Income from income tax, including minimum turnover tax, resulting from income tax settlements in the tax group (acc. 794) | L89: =C89 -> 80 | M89: =E89 -> 0 | N89: =G89 -> 0 | O89: =I89 -> 0 | Q89: 22. Income from income tax, including minimum turnover tax, resulting from income tax settlements in the tax group | R89: 0 | T89: 0 | V89: 0
L90: =C90 -> 0 | M90: =E90 -> 0 | N90: =G90 -> 0 | O90: =I90 -> 0 | R90: 0 | T90: 0 | V90: 0
B91: 23. Cheltuieli cu impozitul pe profit la nivelul impozitului minim pe cifra de afaceri (ct 697) | C91: 81 | E91: 0 | G91: 0 | I91: 0 | K91: 23. Expenses with income tax at the level of the minimum turnover tax (acc. 697) | L91: =C91 -> 81 | M91: =E91 -> 0 | N91: =G91 -> 0 | O91: =I91 -> 0 | Q91: 23. Expenses with income tax at the level of the minimum turnover tax | R91: 0 | T91: 0 | V91: 0
B92: 24. Alte impozite neprezentate la elementele de mai sus (ct 698) | C92: 82 | E92: 0 | G92: 0 | I92: 0 | K92: 24. Other taxes not included in the captions above (acc. 698) | L92: =C92 -> 82 | M92: =E92 -> 0 | N92: =G92 -> 0 | O92: =I92 -> 0 | Q92: 24. Other taxes not included in the captions above | R92: 0 | T92: 0 | V92: 0
B93: PROFITUL SAU PIERDEREA NET(Ă) A EXERCIŢIULUI FINANCIAR: - Profit (rd. 76 – 78 – 79 – 81 – 82 + 80) | C93: 83 | E93: 6423717 | G93: 0 | I93: 1789174 | K93: NET PROFIT OR LOSS FOR THE REPORTING PERIOD - Profit (rows 76 – 78 – 79 – 81 – 82 + 80) | L93: =C93 -> 83 | M93: =E93 -> 6423717 | N93: =G93 -> 0 | O93: =I93 -> 1789174 | Q93: NET PROFIT OR LOSS FOR THE REPORTING PERIOD - Profit | R93: 1975137.2 | S93: 0.051083378 | T93: 1291199.4 | U93: 0.034025688 | V93: 359705.27 | W93: 0.010393742
B94: - Pierdere (rd. 77 + 78 + 79 + 81 + 82 - 80); (rd. 78 + 79 + 81 + 82 – 76 – 80) | C94: 84 | E94: 0 | G94: 0 | I94: 0 | K94: - Loss (rows 77 + 78 + 79 + 81 + 82 - 80); (rows 78 + 79 + 81 + 82 – 76 – 80) | L94: =C94 -> 84 | M94: =E94 -> 0 | N94: =G94 -> 0 | O94: =I94 -> 0 | Q94: - Loss | R94: 0 | T94: 0 | V94: 0
N95: =G95 -> 0
N96: =G96 -> 0
B97: Rezultatul Exercitiului B/S (rd 98 - rd 99) | E97: 6423717 | G97: 0 | I97: 1789174 | K97: Profit/loss B/S (row 98 - row 99) | M97: =E97 -> 6423717 | N97: =G97 -> 0 | O97: =I97 -> 1789174 | Q97: Growth in % | T97: -0.34627357 | V97: -0.72141772
B98: Rezultatul Exercitiului P&L (rd 69 - rd 70) | E98: 6423717 | G98: 0 | I98: 1789174 | K98: Profit/loss P&L (rd 68 - rd 69) | M98: =E98 -> 6423717 | N98: =G98 -> 0 | O98: =I98 -> 1789174
Q101: EBIT | R101: 2496145.5 | T101: 1744048.4 | V101: 551871.53
R102: 0.064558322 | T102: 0.045959166 | V102: 0.015946418
Q103: EBITDA | R103: 5356188.7 | T103: 4654433.6 | V103: 3053975.7
R104: 0.13852821 | T104: 0.12265364 | V104: 0.088245124
...
